{
	"resources": {
		"trolleyContents": {
			"type": "trolleyContents",
			"data": {
				"basketId": "825479033_2065",
				"storeId": "2065",
				"orderNo": "825479033",
				"guidePrice": 2.3,
				"savings": 0,
				"staffDiscount": null,
				"totalItems": 3,
				"constraints": {
					"maxItemCount": 80
				},
				"issues": null,
				"shoppingMethod": "delivery",
				"isAmendBasket": false,
				"IsBagless": true,
				"amendExpiry": null,
				"amendOrderId": null,
				"canExtendSlot": true,
				"deliveryAddress": {
					"name": "Home",
					"addressId": "57688547",
					"addressLine1": null,
					"isBusinessAddress": false,
					"isBlockedAddress": false
				},
				"collectionLocation": {
					"postcode": "CB249LJ"
				},
				"deliveryPreferences": {
					"deliveryInstruction": "",
					"isBagless": true,
					"mobilePhone": "07843203594",
					"dayPhone": "07843203594",
					"eveningPhone": "07843203594"
				},
				"customerPreferences": {
					"substituteAllItems": true
				},
				"slot": null,
				"previousSlot": null,
				"charges": {
					"surcharge": 4,
					"minimumBasketValue": 40,
					"bagCharge": 0.4
				},
				"subscription": {
					"planName": "Any day 6-Month",
					"planId": 34,
					"planType": "anytime",
					"planDurationInMonths": 6,
					"applicableDays": [1, 2, 3, 4, 5, 6, 7],
					"status": "Active",
					"valid": true,
					"basketvalue": "0.00",
					"freeSameDayDelivery": false,
					"isTrialPlan": false
				},
				"promotions": [],
				"availableShoppingMethods": ["delivery", "collection"],
				"items": [{
					"quantity": 1,
					"cost": 0.55,
					"weight": 0,
					"originalQuantity": 0,
					"originalWeight": 0,
					"isNewlyAdded": true,
					"substitutionOption": "FindSuitableAlternative",
					"pickerNote": "",
					"customerUnitChoice": "pcs",
					"itemLimitReached": false,
					"groupLimitReached": false,
					"groupBulkBuyQuantity": 1,
					"product": {
						"id": "254878476",
						"aisleId": "b;Rm9vZCUyMEN1cGJvYXJkJTdDRHJpZWQlMjBQYXN0YSwlMjBSaWNlLCUyME5vb2RsZXMlMjAmJTIwQ291cyUyMENvdXMlN0NQYXN0YSUyMCYlMjBTcGFnaGV0dGk=",
						"aisleName": "Pasta & Spaghetti",
						"shelfId": "b;Rm9vZCUyMEN1cGJvYXJkJTdDRHJpZWQlMjBQYXN0YSwlMjBSaWNlLCUyME5vb2RsZXMlMjAmJTIwQ291cyUyMENvdXMlN0NQYXN0YSUyMCYlMjBTcGFnaGV0dGklN0NQYXN0YSUyMFNoYXBlcw==",
						"shelfName": "Pasta Shapes",
						"baseProductId": "50687061",
						"title": "Tesco Farfalle Pasta Bows 500G",
						"brandName": "Tesco",
						"shortDescription": null,
						"defaultImageUrl": "https://img.tesco.com/Groceries/pi/102/5000119300102/IDShot_225x225.jpg",
						"departmentName": "Dried Pasta, Rice, Noodles & Cous Cous",
						"displayType": "Quantity",
						"productType": "SingleProduct",
						"averageWeight": null,
						"bulkBuyLimit": 3,
						"groupBulkBuyLimit": 0,
						"bulkBuyLimitMessage": "You are able to order a maximum of 3 of this item",
						"bulkBuyLimitGroupId": "G00030670",
						"timeRestrictedDelivery": null,
						"restrictedDelivery": null,
						"isForSale": true,
						"isInFavourites": true,
						"isRestrictedOrderAmendment": null,
						"status": "AvailableForSale",
						"maxWeight": 0,
						"minWeight": 0,
						"increment": 0,
						"catchWeightList": null,
						"restrictions": [],
						"price": 0.55,
						"unitPrice": 1.1,
						"unitOfMeasure": "kg",
						"substitutions": []
					},
					"promotions": []
				}, {
					"quantity": 1,
					"cost": 0.85,
					"weight": 0,
					"originalQuantity": 0,
					"originalWeight": 0,
					"isNewlyAdded": true,
					"substitutionOption": "FindSuitableAlternative",
					"pickerNote": "",
					"customerUnitChoice": "pcs",
					"itemLimitReached": false,
					"groupLimitReached": false,
					"groupBulkBuyQuantity": 1,
					"product": {
						"id": "302872830",
						"aisleId": "b;RnJvemVuJTIwRm9vZCU3Q0ljZSUyMENyZWFtLCUyMEljZSUyMExvbGxpZXMlMjAmJTIwRnJvemVuJTIwRGVzc2VydHMlN0NJY2UlMjBMb2xsaWVz",
						"aisleName": "Ice Lollies",
						"shelfId": "b;RnJvemVuJTIwRm9vZCU3Q0ljZSUyMENyZWFtLCUyMEljZSUyMExvbGxpZXMlMjAmJTIwRnJvemVuJTIwRGVzc2VydHMlN0NJY2UlMjBMb2xsaWVzJTdDSWNlJTIwTG9sbGllcw==",
						"shelfName": "Ice Lollies",
						"baseProductId": "86278283",
						"title": "Ms. Molly's Assorted Fruit Lollies 8X35ml",
						"brandName": "Ms Mollys",
						"shortDescription": null,
						"defaultImageUrl": "https://img.tesco.com/Groceries/pi/251/5057967137251/IDShot_225x225.jpg",
						"departmentName": "Ice Cream, Ice Lollies & Frozen Desserts",
						"displayType": "Quantity",
						"productType": "SingleProduct",
						"averageWeight": null,
						"bulkBuyLimit": 99,
						"groupBulkBuyLimit": 0,
						"bulkBuyLimitMessage": "Sorry, there is a limit of 99 on this product",
						"bulkBuyLimitGroupId": null,
						"timeRestrictedDelivery": null,
						"restrictedDelivery": null,
						"isForSale": true,
						"isInFavourites": false,
						"isRestrictedOrderAmendment": null,
						"status": "AvailableForSale",
						"maxWeight": 0,
						"minWeight": 0,
						"increment": 0,
						"catchWeightList": null,
						"restrictions": [],
						"price": 0.85,
						"unitPrice": 0.304,
						"unitOfMeasure": "100ml",
						"substitutions": []
					},
					"promotions": []
				}, {
					"quantity": 1,
					"cost": 0.9,
					"weight": 0,
					"originalQuantity": 0,
					"originalWeight": 0,
					"isNewlyAdded": true,
					"substitutionOption": "FindSuitableAlternative",
					"pickerNote": "",
					"customerUnitChoice": "pcs",
					"itemLimitReached": false,
					"groupLimitReached": false,
					"groupBulkBuyQuantity": 1,
					"product": {
						"id": "285212132",
						"aisleId": "b;RnJlc2glMjBGb29kJTdDRnJlc2glMjBTYWxhZCUyMCYlMjBEaXBzJTdDVG9tYXRvZXM=",
						"aisleName": "Tomatoes",
						"shelfId": "b;RnJlc2glMjBGb29kJTdDRnJlc2glMjBTYWxhZCUyMCYlMjBEaXBzJTdDVG9tYXRvZXMlN0NCYWJ5JTIwJiUyMENoZXJyeSUyMFRvbWF0b2Vz",
						"shelfName": "Baby & Cherry Tomatoes",
						"baseProductId": "77454543",
						"title": "Tesco Cherry Tomatoes 330G",
						"brandName": "Tesco",
						"shortDescription": null,
						"defaultImageUrl": "https://img.tesco.com/Groceries/pi/534/0000010032534/IDShot_225x225.jpg",
						"departmentName": "Fresh Salad & Dips",
						"displayType": "Quantity",
						"productType": "SingleProduct",
						"averageWeight": null,
						"bulkBuyLimit": 99,
						"groupBulkBuyLimit": 0,
						"bulkBuyLimitMessage": "Sorry, there is a limit of 99 on this product",
						"bulkBuyLimitGroupId": null,
						"timeRestrictedDelivery": null,
						"restrictedDelivery": null,
						"isForSale": true,
						"isInFavourites": true,
						"isRestrictedOrderAmendment": null,
						"status": "AvailableForSale",
						"maxWeight": 0,
						"minWeight": 0,
						"increment": 0,
						"catchWeightList": null,
						"restrictions": [],
						"price": 0.9,
						"unitPrice": 2.73,
						"unitOfMeasure": "kg",
						"substitutions": []
					},
					"promotions": []
				}]
			},
			"params": {},
			"hash": "5591176659614121"
		},
		"slotGroup": {
			"type": "slotGroup",
			"data": {
				"deliverySlotGroups": [1, 4]
			},
			"params": {},
			"hash": "6685042701469245"
		},
		"availableShoppingMethods": {
			"type": "availableShoppingMethods",
			"data": ["delivery", "collection"],
			"params": {},
			"hash": "73175575410779"
		},
		"dcsPage": {
			"type": "dcsPage",
			"data": {
				"pageName": "/GHS-UK/slots",
				"pageTitle": null,
				"keyword": null,
				"description": null,
				"content": {
					"top": [{
						"type": "Panel",
						"props": {
							"catId": null,
							"ruleId": "",
							"contentId": null
						},
						"children": [{
							"type": "SlimTradeBanner",
							"props": {
								"catId": "01",
								"ruleId": "defaultClientType",
								"contentId": "19293239-0d47-4566-b88d-3f2e69fab85c",
								"background": {},
								"bannerColor": {
									"backgroundColor": "#00539f"
								},
								"brandLogo": {},
								"callToAction": {
									"mobile": {
										"backgroundColor": "#00539f",
										"textColor": "#00539f"
									},
									"desktop": {
										"backgroundColor": "#00539f",
										"textColor": "#00539f"
									}
								},
								"eventPing": {},
								"headline": "In self-isolation? Please let us know",
								"link": {
									"openInNewWindow": "no"
								},
								"panelColor": {
									"backgroundColor": "#00539f"
								},
								"priority": "high",
								"product1": {},
								"product2": {},
								"subHeadline": "Just tell us via the delivery instructions box near the bottom of this page",
								"textColor": {
									"color": "#ffffff"
								},
								"valueTile": {
									"is_asterisk": false,
									"is_flat_tile": false
								},
								"placement": 1,
								"posInPanel": 1,
								"segments": ["u-li"],
								"currentUrl": "/delivery/2020-04-21?slotGroup=1"
							},
							"children": null
						}]
					}],
					"bottom": [{
						"type": "Panel",
						"props": {
							"ruleId": ""
						},
						"children": [{
							"type": "DfpBanner",
							"props": {
								"ruleId": "",
								"hideAd": true,
								"placement": 2,
								"posInPanel": 1,
								"segments": ["u-li"],
								"currentUrl": "/delivery/2020-04-21?slotGroup=1"
							},
							"children": null
						}]
					}]
				}
			},
			"params": {},
			"hash": "3908414150828534"
		},
		"orderList": {
			"type": "orderList",
			"data": {
				"recentOrders": [{
					"id": "117608909_2065",
					"formattedOrderId": "117608909",
					"orderNo": "117608909",
					"status": "Delivered",
					"guidePrice": 216.01,
					"shoppingMethod": "delivery",
					"confirmationDateTime": null,
					"slot": {
						"start": "2020-03-04T21:00:00Z",
						"end": "2020-03-04T22:00:00Z",
						"expiry": "2020-03-04T13:15:00Z",
						"locationId": "2065",
						"countdown": null
					},
					"amendExpiryTimeStamp": "2020-03-04T13:00:00.000Z",
					"address": {
						"name": "Home",
						"addressLine1": "31 Saffron Road",
						"addressLine2": "Histon",
						"addressLine3": "Cambridge",
						"addressLine4": "CB249LJ"
					}
				}, {
					"id": "117614010_2065",
					"formattedOrderId": "117614010",
					"orderNo": "117614010",
					"status": "Delivered",
					"guidePrice": 142.45,
					"shoppingMethod": "delivery",
					"confirmationDateTime": null,
					"slot": {
						"start": "2020-03-13T20:00:00Z",
						"end": "2020-03-13T21:00:00Z",
						"expiry": "2020-03-13T00:01:00Z",
						"locationId": "2065",
						"countdown": null
					},
					"amendExpiryTimeStamp": "2020-03-12T23:46:00.000Z",
					"address": {
						"name": "Home",
						"addressLine1": "31 Saffron Road",
						"addressLine2": "Histon",
						"addressLine3": "Cambridge",
						"addressLine4": "CB249LJ"
					}
				}, {
					"id": "117621671_2065",
					"formattedOrderId": "117621671",
					"orderNo": "117621671",
					"status": "Delivered",
					"guidePrice": 146.1,
					"shoppingMethod": "delivery",
					"confirmationDateTime": null,
					"slot": {
						"start": "2020-03-25T20:00:00Z",
						"end": "2020-03-25T21:00:00Z",
						"expiry": "2020-03-25T00:01:00Z",
						"locationId": "2065",
						"countdown": null
					},
					"amendExpiryTimeStamp": "2020-03-24T23:46:00.000Z",
					"address": {
						"name": "Home",
						"addressLine1": "31 Saffron Road",
						"addressLine2": "Histon",
						"addressLine3": "Cambridge",
						"addressLine4": "CB249LJ"
					}
				}, {
					"id": "393892108_5379",
					"formattedOrderId": "393892108",
					"orderNo": "393892108",
					"status": "Delivered",
					"guidePrice": 113.48,
					"shoppingMethod": "delivery",
					"confirmationDateTime": null,
					"slot": {
						"start": "2020-03-31T08:00:00Z",
						"end": "2020-03-31T09:00:00Z",
						"expiry": "2020-03-30T23:01:00Z",
						"locationId": "5379",
						"countdown": null
					},
					"amendExpiryTimeStamp": "2020-03-30T22:46:00.000Z",
					"address": {
						"name": "The Murphys Nottingham",
						"addressLine1": "511 Mansfield Road",
						"addressLine2": "Redhill",
						"addressLine3": "NOTTINGHAM",
						"addressLine4": "NG58PG"
					}
				}, {
					"id": "117623550_2065",
					"formattedOrderId": "117623550",
					"orderNo": "117623550",
					"status": "Delivered",
					"guidePrice": 96.37,
					"shoppingMethod": "delivery",
					"confirmationDateTime": null,
					"slot": {
						"start": "2020-04-01T19:00:00Z",
						"end": "2020-04-01T20:00:00Z",
						"expiry": "2020-03-31T23:01:00Z",
						"locationId": "2065",
						"countdown": null
					},
					"amendExpiryTimeStamp": "2020-03-31T22:46:00.000Z",
					"address": {
						"name": "Home",
						"addressLine1": "31 Saffron Road",
						"addressLine2": "Histon",
						"addressLine3": "Cambridge",
						"addressLine4": "CB249LJ"
					}
				}, {
					"id": "117632750_2065",
					"formattedOrderId": "117632750",
					"orderNo": "117632750",
					"status": "Delivered",
					"guidePrice": 122.05,
					"shoppingMethod": "delivery",
					"confirmationDateTime": null,
					"slot": {
						"start": "2020-04-04T12:00:00Z",
						"end": "2020-04-04T13:00:00Z",
						"expiry": "2020-04-03T23:01:00Z",
						"locationId": "2065",
						"countdown": null
					},
					"amendExpiryTimeStamp": "2020-04-03T22:46:00.000Z",
					"address": {
						"name": "Home",
						"addressLine1": "31 Saffron Road",
						"addressLine2": "Histon",
						"addressLine3": "Cambridge",
						"addressLine4": "CB249LJ"
					}
				}],
				"pendingOrders": [],
				"noOfPendingOrders": 0,
				"pendingOrdersByDate": {},
				"currentWismoOrder": null
			},
			"params": {},
			"hash": "736073023857832"
		},
		"slot": {
			"type": "slot",
			"data": {
				"deliverySlotGroups": [1, 4],
				"basket": {
					"deliveryPreferences": {
						"deliveryInstruction": ""
					}
				},
				"delivery": [{
					"slotId": "IzIwNjUtNTc2ODg1NDcjMjA2NSMyMDIwLTA0LTIxVDA3OjAwOjAwWiMyMDIwLTA0LTIxVDA4OjAwOjAwWiM2IzIwMjAtMDQtMjBUMjM6MDE6MDBaIw==",
					"start": "2020-04-21T07:00:00.000Z",
					"end": "2020-04-21T08:00:00.000Z",
					"expiry": "2020-04-20T23:01:00Z",
					"charge": 6,
					"status": "Unavailable",
					"group": 1,
					"locationId": "2065-57688547"
				}, {
					"slotId": "IzIwNjUtNTc2ODg1NDcjMjA2NSMyMDIwLTA0LTIxVDA4OjAwOjAwWiMyMDIwLTA0LTIxVDA5OjAwOjAwWiM2IzIwMjAtMDQtMjBUMjM6MDE6MDBaIw==",
					"start": "2020-04-21T08:00:00.000Z",
					"end": "2020-04-21T09:00:00.000Z",
					"expiry": "2020-04-20T23:01:00Z",
					"charge": 6,
					"status": "Unavailable",
					"group": 1,
					"locationId": "2065-57688547"
				}, {
					"slotId": "IzIwNjUtNTc2ODg1NDcjMjA2NSMyMDIwLTA0LTIxVDA5OjAwOjAwWiMyMDIwLTA0LTIxVDEwOjAwOjAwWiM2IzIwMjAtMDQtMjBUMjM6MDE6MDBaIw==",
					"start": "2020-04-21T09:00:00.000Z",
					"end": "2020-04-21T10:00:00.000Z",
					"expiry": "2020-04-20T23:01:00Z",
					"charge": 6,
					"status": "Unavailable",
					"group": 1,
					"locationId": "2065-57688547"
				}, {
					"slotId": "IzIwNjUtNTc2ODg1NDcjMjA2NSMyMDIwLTA0LTIxVDEwOjAwOjAwWiMyMDIwLTA0LTIxVDExOjAwOjAwWiM1IzIwMjAtMDQtMjBUMjM6MDE6MDBaIw==",
					"start": "2020-04-21T10:00:00.000Z",
					"end": "2020-04-21T11:00:00.000Z",
					"expiry": "2020-04-20T23:01:00Z",
					"charge": 5,
					"status": "Unavailable",
					"group": 1,
					"locationId": "2065-57688547"
				}, {
					"slotId": "IzIwNjUtNTc2ODg1NDcjMjA2NSMyMDIwLTA0LTIxVDExOjAwOjAwWiMyMDIwLTA0LTIxVDEyOjAwOjAwWiM0IzIwMjAtMDQtMjBUMjM6MDE6MDBaIw==",
					"start": "2020-04-21T11:00:00.000Z",
					"end": "2020-04-21T12:00:00.000Z",
					"expiry": "2020-04-20T23:01:00Z",
					"charge": 4,
					"status": "Unavailable",
					"group": 1,
					"locationId": "2065-57688547"
				}, {
					"slotId": "IzIwNjUtNTc2ODg1NDcjMjA2NSMyMDIwLTA0LTIxVDEyOjAwOjAwWiMyMDIwLTA0LTIxVDEzOjAwOjAwWiM0IzIwMjAtMDQtMjBUMjM6MDE6MDBaIw==",
					"start": "2020-04-21T12:00:00.000Z",
					"end": "2020-04-21T13:00:00.000Z",
					"expiry": "2020-04-20T23:01:00Z",
					"charge": 4,
					"status": "Unavailable",
					"group": 1,
					"locationId": "2065-57688547"
				}, {
					"slotId": "IzIwNjUtNTc2ODg1NDcjMjA2NSMyMDIwLTA0LTIxVDEzOjAwOjAwWiMyMDIwLTA0LTIxVDE0OjAwOjAwWiMzLjUjMjAyMC0wNC0yMFQyMzowMTowMFoj",
					"start": "2020-04-21T13:00:00.000Z",
					"end": "2020-04-21T14:00:00.000Z",
					"expiry": "2020-04-20T23:01:00Z",
					"charge": 3.5,
					"status": "Unavailable",
					"group": 1,
					"locationId": "2065-57688547"
				}, {
					"slotId": "IzIwNjUtNTc2ODg1NDcjMjA2NSMyMDIwLTA0LTIxVDE0OjAwOjAwWiMyMDIwLTA0LTIxVDE1OjAwOjAwWiMzLjUjMjAyMC0wNC0yMFQyMzowMTowMFoj",
					"start": "2020-04-21T14:00:00.000Z",
					"end": "2020-04-21T15:00:00.000Z",
					"expiry": "2020-04-20T23:01:00Z",
					"charge": 3.5,
					"status": "Unavailable",
					"group": 1,
					"locationId": "2065-57688547"
				}, {
					"slotId": "IzIwNjUtNTc2ODg1NDcjMjA2NSMyMDIwLTA0LTIxVDE1OjAwOjAwWiMyMDIwLTA0LTIxVDE2OjAwOjAwWiMzIzIwMjAtMDQtMjBUMjM6MDE6MDBaIw==",
					"start": "2020-04-21T15:00:00.000Z",
					"end": "2020-04-21T16:00:00.000Z",
					"expiry": "2020-04-20T23:01:00Z",
					"charge": 3,
					"status": "Unavailable",
					"group": 1,
					"locationId": "2065-57688547"
				}, {
					"slotId": "IzIwNjUtNTc2ODg1NDcjMjA2NSMyMDIwLTA0LTIxVDE2OjAwOjAwWiMyMDIwLTA0LTIxVDE3OjAwOjAwWiMzLjUjMjAyMC0wNC0yMFQyMzowMTowMFoj",
					"start": "2020-04-21T16:00:00.000Z",
					"end": "2020-04-21T17:00:00.000Z",
					"expiry": "2020-04-20T23:01:00Z",
					"charge": 3.5,
					"status": "Unavailable",
					"group": 1,
					"locationId": "2065-57688547"
				}, {
					"slotId": "IzIwNjUtNTc2ODg1NDcjMjA2NSMyMDIwLTA0LTIxVDE3OjAwOjAwWiMyMDIwLTA0LTIxVDE4OjAwOjAwWiMzIzIwMjAtMDQtMjBUMjM6MDE6MDBaIw==",
					"start": "2020-04-21T17:00:00.000Z",
					"end": "2020-04-21T18:00:00.000Z",
					"expiry": "2020-04-20T23:01:00Z",
					"charge": 3,
					"status": "Unavailable",
					"group": 1,
					"locationId": "2065-57688547"
				}, {
					"slotId": "IzIwNjUtNTc2ODg1NDcjMjA2NSMyMDIwLTA0LTIxVDE4OjAwOjAwWiMyMDIwLTA0LTIxVDE5OjAwOjAwWiMzLjUjMjAyMC0wNC0yMFQyMzowMTowMFoj",
					"start": "2020-04-21T18:00:00.000Z",
					"end": "2020-04-21T19:00:00.000Z",
					"expiry": "2020-04-20T23:01:00Z",
					"charge": 3.5,
					"status": "Unavailable",
					"group": 1,
					"locationId": "2065-57688547"
				}, {
					"slotId": "IzIwNjUtNTc2ODg1NDcjMjA2NSMyMDIwLTA0LTIxVDE5OjAwOjAwWiMyMDIwLTA0LTIxVDIwOjAwOjAwWiMyLjUjMjAyMC0wNC0yMFQyMzowMTowMFoj",
					"start": "2020-04-21T19:00:00.000Z",
					"end": "2020-04-21T20:00:00.000Z",
					"expiry": "2020-04-20T23:01:00Z",
					"charge": 2.5,
					"status": "Unavailable",
					"group": 1,
					"locationId": "2065-57688547"
				}, {
					"slotId": "IzIwNjUtNTc2ODg1NDcjMjA2NSMyMDIwLTA0LTIxVDIwOjAwOjAwWiMyMDIwLTA0LTIxVDIxOjAwOjAwWiMyIzIwMjAtMDQtMjBUMjM6MDE6MDBaIw==",
					"start": "2020-04-21T20:00:00.000Z",
					"end": "2020-04-21T21:00:00.000Z",
					"expiry": "2020-04-20T23:01:00Z",
					"charge": 2,
					"status": "Unavailable",
					"group": 1,
					"locationId": "2065-57688547"
				}, {
					"slotId": "IzIwNjUtNTc2ODg1NDcjMjA2NSMyMDIwLTA0LTIxVDIxOjAwOjAwWiMyMDIwLTA0LTIxVDIyOjAwOjAwWiMyIzIwMjAtMDQtMjBUMjM6MDE6MDBaIw==",
					"start": "2020-04-21T21:00:00.000Z",
					"end": "2020-04-21T22:00:00.000Z",
					"expiry": "2020-04-20T23:01:00Z",
					"charge": 2,
					"status": "Unavailable",
					"group": 1,
					"locationId": "2065-57688547"
				}, {
					"slotId": "IzIwNjUtNTc2ODg1NDcjMjA2NSMyMDIwLTA0LTIyVDA3OjAwOjAwWiMyMDIwLTA0LTIyVDA4OjAwOjAwWiM0LjUjMjAyMC0wNC0yMVQyMzowMTowMFoj",
					"start": "2020-04-22T07:00:00.000Z",
					"end": "2020-04-22T08:00:00.000Z",
					"expiry": "2020-04-21T23:01:00Z",
					"charge": 4.5,
					"status": "Unavailable",
					"group": 1,
					"locationId": "2065-57688547"
				}, {
					"slotId": "IzIwNjUtNTc2ODg1NDcjMjA2NSMyMDIwLTA0LTIyVDA4OjAwOjAwWiMyMDIwLTA0LTIyVDA5OjAwOjAwWiM0IzIwMjAtMDQtMjFUMjM6MDE6MDBaIw==",
					"start": "2020-04-22T08:00:00.000Z",
					"end": "2020-04-22T09:00:00.000Z",
					"expiry": "2020-04-21T23:01:00Z",
					"charge": 4,
					"status": "Unavailable",
					"group": 1,
					"locationId": "2065-57688547"
				}, {
					"slotId": "IzIwNjUtNTc2ODg1NDcjMjA2NSMyMDIwLTA0LTIyVDA5OjAwOjAwWiMyMDIwLTA0LTIyVDEwOjAwOjAwWiMzIzIwMjAtMDQtMjFUMjM6MDE6MDBaIw==",
					"start": "2020-04-22T09:00:00.000Z",
					"end": "2020-04-22T10:00:00.000Z",
					"expiry": "2020-04-21T23:01:00Z",
					"charge": 3,
					"status": "Unavailable",
					"group": 1,
					"locationId": "2065-57688547"
				}, {
					"slotId": "IzIwNjUtNTc2ODg1NDcjMjA2NSMyMDIwLTA0LTIyVDEwOjAwOjAwWiMyMDIwLTA0LTIyVDExOjAwOjAwWiMzIzIwMjAtMDQtMjFUMjM6MDE6MDBaIw==",
					"start": "2020-04-22T10:00:00.000Z",
					"end": "2020-04-22T11:00:00.000Z",
					"expiry": "2020-04-21T23:01:00Z",
					"charge": 3,
					"status": "Unavailable",
					"group": 1,
					"locationId": "2065-57688547"
				}, {
					"slotId": "IzIwNjUtNTc2ODg1NDcjMjA2NSMyMDIwLTA0LTIyVDExOjAwOjAwWiMyMDIwLTA0LTIyVDEyOjAwOjAwWiMyLjUjMjAyMC0wNC0yMVQyMzowMTowMFoj",
					"start": "2020-04-22T11:00:00.000Z",
					"end": "2020-04-22T12:00:00.000Z",
					"expiry": "2020-04-21T23:01:00Z",
					"charge": 2.5,
					"status": "Unavailable",
					"group": 1,
					"locationId": "2065-57688547"
				}, {
					"slotId": "IzIwNjUtNTc2ODg1NDcjMjA2NSMyMDIwLTA0LTIyVDEyOjAwOjAwWiMyMDIwLTA0LTIyVDEzOjAwOjAwWiMyIzIwMjAtMDQtMjFUMjM6MDE6MDBaIw==",
					"start": "2020-04-22T12:00:00.000Z",
					"end": "2020-04-22T13:00:00.000Z",
					"expiry": "2020-04-21T23:01:00Z",
					"charge": 2,
					"status": "Unavailable",
					"group": 1,
					"locationId": "2065-57688547"
				}, {
					"slotId": "IzIwNjUtNTc2ODg1NDcjMjA2NSMyMDIwLTA0LTIyVDEzOjAwOjAwWiMyMDIwLTA0LTIyVDE0OjAwOjAwWiMyLjUjMjAyMC0wNC0yMVQyMzowMTowMFoj",
					"start": "2020-04-22T13:00:00.000Z",
					"end": "2020-04-22T14:00:00.000Z",
					"expiry": "2020-04-21T23:01:00Z",
					"charge": 2.5,
					"status": "Unavailable",
					"group": 1,
					"locationId": "2065-57688547"
				}, {
					"slotId": "IzIwNjUtNTc2ODg1NDcjMjA2NSMyMDIwLTA0LTIyVDE0OjAwOjAwWiMyMDIwLTA0LTIyVDE1OjAwOjAwWiMyIzIwMjAtMDQtMjFUMjM6MDE6MDBaIw==",
					"start": "2020-04-22T14:00:00.000Z",
					"end": "2020-04-22T15:00:00.000Z",
					"expiry": "2020-04-21T23:01:00Z",
					"charge": 2,
					"status": "Unavailable",
					"group": 1,
					"locationId": "2065-57688547"
				}, {
					"slotId": "IzIwNjUtNTc2ODg1NDcjMjA2NSMyMDIwLTA0LTIyVDE1OjAwOjAwWiMyMDIwLTA0LTIyVDE2OjAwOjAwWiMyIzIwMjAtMDQtMjFUMjM6MDE6MDBaIw==",
					"start": "2020-04-22T15:00:00.000Z",
					"end": "2020-04-22T16:00:00.000Z",
					"expiry": "2020-04-21T23:01:00Z",
					"charge": 2,
					"status": "Unavailable",
					"group": 1,
					"locationId": "2065-57688547"
				}, {
					"slotId": "IzIwNjUtNTc2ODg1NDcjMjA2NSMyMDIwLTA0LTIyVDE2OjAwOjAwWiMyMDIwLTA0LTIyVDE3OjAwOjAwWiMyLjUjMjAyMC0wNC0yMVQyMzowMTowMFoj",
					"start": "2020-04-22T16:00:00.000Z",
					"end": "2020-04-22T17:00:00.000Z",
					"expiry": "2020-04-21T23:01:00Z",
					"charge": 2.5,
					"status": "Unavailable",
					"group": 1,
					"locationId": "2065-57688547"
				}, {
					"slotId": "IzIwNjUtNTc2ODg1NDcjMjA2NSMyMDIwLTA0LTIyVDE3OjAwOjAwWiMyMDIwLTA0LTIyVDE4OjAwOjAwWiMyIzIwMjAtMDQtMjFUMjM6MDE6MDBaIw==",
					"start": "2020-04-22T17:00:00.000Z",
					"end": "2020-04-22T18:00:00.000Z",
					"expiry": "2020-04-21T23:01:00Z",
					"charge": 2,
					"status": "Unavailable",
					"group": 1,
					"locationId": "2065-57688547"
				}, {
					"slotId": "IzIwNjUtNTc2ODg1NDcjMjA2NSMyMDIwLTA0LTIyVDE4OjAwOjAwWiMyMDIwLTA0LTIyVDE5OjAwOjAwWiMyIzIwMjAtMDQtMjFUMjM6MDE6MDBaIw==",
					"start": "2020-04-22T18:00:00.000Z",
					"end": "2020-04-22T19:00:00.000Z",
					"expiry": "2020-04-21T23:01:00Z",
					"charge": 2,
					"status": "Unavailable",
					"group": 1,
					"locationId": "2065-57688547"
				}, {
					"slotId": "IzIwNjUtNTc2ODg1NDcjMjA2NSMyMDIwLTA0LTIyVDE5OjAwOjAwWiMyMDIwLTA0LTIyVDIwOjAwOjAwWiMyIzIwMjAtMDQtMjFUMjM6MDE6MDBaIw==",
					"start": "2020-04-22T19:00:00.000Z",
					"end": "2020-04-22T20:00:00.000Z",
					"expiry": "2020-04-21T23:01:00Z",
					"charge": 2,
					"status": "Unavailable",
					"group": 1,
					"locationId": "2065-57688547"
				}, {
					"slotId": "IzIwNjUtNTc2ODg1NDcjMjA2NSMyMDIwLTA0LTIyVDIwOjAwOjAwWiMyMDIwLTA0LTIyVDIxOjAwOjAwWiMyIzIwMjAtMDQtMjFUMjM6MDE6MDBaIw==",
					"start": "2020-04-22T20:00:00.000Z",
					"end": "2020-04-22T21:00:00.000Z",
					"expiry": "2020-04-21T23:01:00Z",
					"charge": 2,
					"status": "Unavailable",
					"group": 1,
					"locationId": "2065-57688547"
				}, {
					"slotId": "IzIwNjUtNTc2ODg1NDcjMjA2NSMyMDIwLTA0LTIyVDIxOjAwOjAwWiMyMDIwLTA0LTIyVDIyOjAwOjAwWiMyIzIwMjAtMDQtMjFUMjM6MDE6MDBaIw==",
					"start": "2020-04-22T21:00:00.000Z",
					"end": "2020-04-22T22:00:00.000Z",
					"expiry": "2020-04-21T23:01:00Z",
					"charge": 2,
					"status": "Unavailable",
					"group": 1,
					"locationId": "2065-57688547"
				}, {
					"slotId": "IzIwNjUtNTc2ODg1NDcjMjA2NSMyMDIwLTA0LTIzVDA3OjAwOjAwWiMyMDIwLTA0LTIzVDA4OjAwOjAwWiM2IzIwMjAtMDQtMjJUMjM6MDE6MDBaIw==",
					"start": "2020-04-23T07:00:00.000Z",
					"end": "2020-04-23T08:00:00.000Z",
					"expiry": "2020-04-22T23:01:00Z",
					"charge": 6,
					"status": "Unavailable",
					"group": 1,
					"locationId": "2065-57688547"
				}, {
					"slotId": "IzIwNjUtNTc2ODg1NDcjMjA2NSMyMDIwLTA0LTIzVDA4OjAwOjAwWiMyMDIwLTA0LTIzVDA5OjAwOjAwWiM2IzIwMjAtMDQtMjJUMjM6MDE6MDBaIw==",
					"start": "2020-04-23T08:00:00.000Z",
					"end": "2020-04-23T09:00:00.000Z",
					"expiry": "2020-04-22T23:01:00Z",
					"charge": 6,
					"status": "Unavailable",
					"group": 1,
					"locationId": "2065-57688547"
				}, {
					"slotId": "IzIwNjUtNTc2ODg1NDcjMjA2NSMyMDIwLTA0LTIzVDA5OjAwOjAwWiMyMDIwLTA0LTIzVDEwOjAwOjAwWiM2IzIwMjAtMDQtMjJUMjM6MDE6MDBaIw==",
					"start": "2020-04-23T09:00:00.000Z",
					"end": "2020-04-23T10:00:00.000Z",
					"expiry": "2020-04-22T23:01:00Z",
					"charge": 6,
					"status": "Unavailable",
					"group": 1,
					"locationId": "2065-57688547"
				}, {
					"slotId": "IzIwNjUtNTc2ODg1NDcjMjA2NSMyMDIwLTA0LTIzVDEwOjAwOjAwWiMyMDIwLTA0LTIzVDExOjAwOjAwWiM1IzIwMjAtMDQtMjJUMjM6MDE6MDBaIw==",
					"start": "2020-04-23T10:00:00.000Z",
					"end": "2020-04-23T11:00:00.000Z",
					"expiry": "2020-04-22T23:01:00Z",
					"charge": 5,
					"status": "Unavailable",
					"group": 1,
					"locationId": "2065-57688547"
				}, {
					"slotId": "IzIwNjUtNTc2ODg1NDcjMjA2NSMyMDIwLTA0LTIzVDExOjAwOjAwWiMyMDIwLTA0LTIzVDEyOjAwOjAwWiM0LjUjMjAyMC0wNC0yMlQyMzowMTowMFoj",
					"start": "2020-04-23T11:00:00.000Z",
					"end": "2020-04-23T12:00:00.000Z",
					"expiry": "2020-04-22T23:01:00Z",
					"charge": 4.5,
					"status": "Unavailable",
					"group": 1,
					"locationId": "2065-57688547"
				}, {
					"slotId": "IzIwNjUtNTc2ODg1NDcjMjA2NSMyMDIwLTA0LTIzVDEyOjAwOjAwWiMyMDIwLTA0LTIzVDEzOjAwOjAwWiM1IzIwMjAtMDQtMjJUMjM6MDE6MDBaIw==",
					"start": "2020-04-23T12:00:00.000Z",
					"end": "2020-04-23T13:00:00.000Z",
					"expiry": "2020-04-22T23:01:00Z",
					"charge": 5,
					"status": "Unavailable",
					"group": 1,
					"locationId": "2065-57688547"
				}, {
					"slotId": "IzIwNjUtNTc2ODg1NDcjMjA2NSMyMDIwLTA0LTIzVDEzOjAwOjAwWiMyMDIwLTA0LTIzVDE0OjAwOjAwWiM0IzIwMjAtMDQtMjJUMjM6MDE6MDBaIw==",
					"start": "2020-04-23T13:00:00.000Z",
					"end": "2020-04-23T14:00:00.000Z",
					"expiry": "2020-04-22T23:01:00Z",
					"charge": 4,
					"status": "Unavailable",
					"group": 1,
					"locationId": "2065-57688547"
				}, {
					"slotId": "IzIwNjUtNTc2ODg1NDcjMjA2NSMyMDIwLTA0LTIzVDE0OjAwOjAwWiMyMDIwLTA0LTIzVDE1OjAwOjAwWiMzLjUjMjAyMC0wNC0yMlQyMzowMTowMFoj",
					"start": "2020-04-23T14:00:00.000Z",
					"end": "2020-04-23T15:00:00.000Z",
					"expiry": "2020-04-22T23:01:00Z",
					"charge": 3.5,
					"status": "Unavailable",
					"group": 1,
					"locationId": "2065-57688547"
				}, {
					"slotId": "IzIwNjUtNTc2ODg1NDcjMjA2NSMyMDIwLTA0LTIzVDE1OjAwOjAwWiMyMDIwLTA0LTIzVDE2OjAwOjAwWiM0LjUjMjAyMC0wNC0yMlQyMzowMTowMFoj",
					"start": "2020-04-23T15:00:00.000Z",
					"end": "2020-04-23T16:00:00.000Z",
					"expiry": "2020-04-22T23:01:00Z",
					"charge": 4.5,
					"status": "Unavailable",
					"group": 1,
					"locationId": "2065-57688547"
				}, {
					"slotId": "IzIwNjUtNTc2ODg1NDcjMjA2NSMyMDIwLTA0LTIzVDE2OjAwOjAwWiMyMDIwLTA0LTIzVDE3OjAwOjAwWiM0LjUjMjAyMC0wNC0yMlQyMzowMTowMFoj",
					"start": "2020-04-23T16:00:00.000Z",
					"end": "2020-04-23T17:00:00.000Z",
					"expiry": "2020-04-22T23:01:00Z",
					"charge": 4.5,
					"status": "Unavailable",
					"group": 1,
					"locationId": "2065-57688547"
				}, {
					"slotId": "IzIwNjUtNTc2ODg1NDcjMjA2NSMyMDIwLTA0LTIzVDE3OjAwOjAwWiMyMDIwLTA0LTIzVDE4OjAwOjAwWiM0IzIwMjAtMDQtMjJUMjM6MDE6MDBaIw==",
					"start": "2020-04-23T17:00:00.000Z",
					"end": "2020-04-23T18:00:00.000Z",
					"expiry": "2020-04-22T23:01:00Z",
					"charge": 4,
					"status": "Unavailable",
					"group": 1,
					"locationId": "2065-57688547"
				}, {
					"slotId": "IzIwNjUtNTc2ODg1NDcjMjA2NSMyMDIwLTA0LTIzVDE4OjAwOjAwWiMyMDIwLTA0LTIzVDE5OjAwOjAwWiMzIzIwMjAtMDQtMjJUMjM6MDE6MDBaIw==",
					"start": "2020-04-23T18:00:00.000Z",
					"end": "2020-04-23T19:00:00.000Z",
					"expiry": "2020-04-22T23:01:00Z",
					"charge": 3,
					"status": "Unavailable",
					"group": 1,
					"locationId": "2065-57688547"
				}, {
					"slotId": "IzIwNjUtNTc2ODg1NDcjMjA2NSMyMDIwLTA0LTIzVDE5OjAwOjAwWiMyMDIwLTA0LTIzVDIwOjAwOjAwWiMzIzIwMjAtMDQtMjJUMjM6MDE6MDBaIw==",
					"start": "2020-04-23T19:00:00.000Z",
					"end": "2020-04-23T20:00:00.000Z",
					"expiry": "2020-04-22T23:01:00Z",
					"charge": 3,
					"status": "Unavailable",
					"group": 1,
					"locationId": "2065-57688547"
				}, {
					"slotId": "IzIwNjUtNTc2ODg1NDcjMjA2NSMyMDIwLTA0LTIzVDIwOjAwOjAwWiMyMDIwLTA0LTIzVDIxOjAwOjAwWiMyIzIwMjAtMDQtMjJUMjM6MDE6MDBaIw==",
					"start": "2020-04-23T20:00:00.000Z",
					"end": "2020-04-23T21:00:00.000Z",
					"expiry": "2020-04-22T23:01:00Z",
					"charge": 2,
					"status": "Unavailable",
					"group": 1,
					"locationId": "2065-57688547"
				}, {
					"slotId": "IzIwNjUtNTc2ODg1NDcjMjA2NSMyMDIwLTA0LTIzVDIxOjAwOjAwWiMyMDIwLTA0LTIzVDIyOjAwOjAwWiMyIzIwMjAtMDQtMjJUMjM6MDE6MDBaIw==",
					"start": "2020-04-23T21:00:00.000Z",
					"end": "2020-04-23T22:00:00.000Z",
					"expiry": "2020-04-22T23:01:00Z",
					"charge": 2,
					"status": "Unavailable",
					"group": 1,
					"locationId": "2065-57688547"
				}, {
					"slotId": "IzIwNjUtNTc2ODg1NDcjMjA2NSMyMDIwLTA0LTI0VDA3OjAwOjAwWiMyMDIwLTA0LTI0VDA4OjAwOjAwWiM3IzIwMjAtMDQtMjNUMjM6MDE6MDBaIw==",
					"start": "2020-04-24T07:00:00.000Z",
					"end": "2020-04-24T08:00:00.000Z",
					"expiry": "2020-04-23T23:01:00Z",
					"charge": 7,
					"status": "Unavailable",
					"group": 1,
					"locationId": "2065-57688547"
				}, {
					"slotId": "IzIwNjUtNTc2ODg1NDcjMjA2NSMyMDIwLTA0LTI0VDA4OjAwOjAwWiMyMDIwLTA0LTI0VDA5OjAwOjAwWiM3IzIwMjAtMDQtMjNUMjM6MDE6MDBaIw==",
					"start": "2020-04-24T08:00:00.000Z",
					"end": "2020-04-24T09:00:00.000Z",
					"expiry": "2020-04-23T23:01:00Z",
					"charge": 7,
					"status": "Unavailable",
					"group": 1,
					"locationId": "2065-57688547"
				}, {
					"slotId": "IzIwNjUtNTc2ODg1NDcjMjA2NSMyMDIwLTA0LTI0VDA5OjAwOjAwWiMyMDIwLTA0LTI0VDEwOjAwOjAwWiM2LjUjMjAyMC0wNC0yM1QyMzowMTowMFoj",
					"start": "2020-04-24T09:00:00.000Z",
					"end": "2020-04-24T10:00:00.000Z",
					"expiry": "2020-04-23T23:01:00Z",
					"charge": 6.5,
					"status": "Unavailable",
					"group": 1,
					"locationId": "2065-57688547"
				}, {
					"slotId": "IzIwNjUtNTc2ODg1NDcjMjA2NSMyMDIwLTA0LTI0VDEwOjAwOjAwWiMyMDIwLTA0LTI0VDExOjAwOjAwWiM2IzIwMjAtMDQtMjNUMjM6MDE6MDBaIw==",
					"start": "2020-04-24T10:00:00.000Z",
					"end": "2020-04-24T11:00:00.000Z",
					"expiry": "2020-04-23T23:01:00Z",
					"charge": 6,
					"status": "Unavailable",
					"group": 1,
					"locationId": "2065-57688547"
				}, {
					"slotId": "IzIwNjUtNTc2ODg1NDcjMjA2NSMyMDIwLTA0LTI0VDExOjAwOjAwWiMyMDIwLTA0LTI0VDEyOjAwOjAwWiM1LjUjMjAyMC0wNC0yM1QyMzowMTowMFoj",
					"start": "2020-04-24T11:00:00.000Z",
					"end": "2020-04-24T12:00:00.000Z",
					"expiry": "2020-04-23T23:01:00Z",
					"charge": 5.5,
					"status": "Unavailable",
					"group": 1,
					"locationId": "2065-57688547"
				}, {
					"slotId": "IzIwNjUtNTc2ODg1NDcjMjA2NSMyMDIwLTA0LTI0VDEyOjAwOjAwWiMyMDIwLTA0LTI0VDEzOjAwOjAwWiM2IzIwMjAtMDQtMjNUMjM6MDE6MDBaIw==",
					"start": "2020-04-24T12:00:00.000Z",
					"end": "2020-04-24T13:00:00.000Z",
					"expiry": "2020-04-23T23:01:00Z",
					"charge": 6,
					"status": "Unavailable",
					"group": 1,
					"locationId": "2065-57688547"
				}, {
					"slotId": "IzIwNjUtNTc2ODg1NDcjMjA2NSMyMDIwLTA0LTI0VDEzOjAwOjAwWiMyMDIwLTA0LTI0VDE0OjAwOjAwWiM1LjUjMjAyMC0wNC0yM1QyMzowMTowMFoj",
					"start": "2020-04-24T13:00:00.000Z",
					"end": "2020-04-24T14:00:00.000Z",
					"expiry": "2020-04-23T23:01:00Z",
					"charge": 5.5,
					"status": "Unavailable",
					"group": 1,
					"locationId": "2065-57688547"
				}, {
					"slotId": "IzIwNjUtNTc2ODg1NDcjMjA2NSMyMDIwLTA0LTI0VDE0OjAwOjAwWiMyMDIwLTA0LTI0VDE1OjAwOjAwWiM1IzIwMjAtMDQtMjNUMjM6MDE6MDBaIw==",
					"start": "2020-04-24T14:00:00.000Z",
					"end": "2020-04-24T15:00:00.000Z",
					"expiry": "2020-04-23T23:01:00Z",
					"charge": 5,
					"status": "Unavailable",
					"group": 1,
					"locationId": "2065-57688547"
				}, {
					"slotId": "IzIwNjUtNTc2ODg1NDcjMjA2NSMyMDIwLTA0LTI0VDE1OjAwOjAwWiMyMDIwLTA0LTI0VDE2OjAwOjAwWiM1IzIwMjAtMDQtMjNUMjM6MDE6MDBaIw==",
					"start": "2020-04-24T15:00:00.000Z",
					"end": "2020-04-24T16:00:00.000Z",
					"expiry": "2020-04-23T23:01:00Z",
					"charge": 5,
					"status": "Unavailable",
					"group": 1,
					"locationId": "2065-57688547"
				}, {
					"slotId": "IzIwNjUtNTc2ODg1NDcjMjA2NSMyMDIwLTA0LTI0VDE2OjAwOjAwWiMyMDIwLTA0LTI0VDE3OjAwOjAwWiM1LjUjMjAyMC0wNC0yM1QyMzowMTowMFoj",
					"start": "2020-04-24T16:00:00.000Z",
					"end": "2020-04-24T17:00:00.000Z",
					"expiry": "2020-04-23T23:01:00Z",
					"charge": 5.5,
					"status": "Unavailable",
					"group": 1,
					"locationId": "2065-57688547"
				}, {
					"slotId": "IzIwNjUtNTc2ODg1NDcjMjA2NSMyMDIwLTA0LTI0VDE3OjAwOjAwWiMyMDIwLTA0LTI0VDE4OjAwOjAwWiM1IzIwMjAtMDQtMjNUMjM6MDE6MDBaIw==",
					"start": "2020-04-24T17:00:00.000Z",
					"end": "2020-04-24T18:00:00.000Z",
					"expiry": "2020-04-23T23:01:00Z",
					"charge": 5,
					"status": "Unavailable",
					"group": 1,
					"locationId": "2065-57688547"
				}, {
					"slotId": "IzIwNjUtNTc2ODg1NDcjMjA2NSMyMDIwLTA0LTI0VDE4OjAwOjAwWiMyMDIwLTA0LTI0VDE5OjAwOjAwWiM1IzIwMjAtMDQtMjNUMjM6MDE6MDBaIw==",
					"start": "2020-04-24T18:00:00.000Z",
					"end": "2020-04-24T19:00:00.000Z",
					"expiry": "2020-04-23T23:01:00Z",
					"charge": 5,
					"status": "Unavailable",
					"group": 1,
					"locationId": "2065-57688547"
				}, {
					"slotId": "IzIwNjUtNTc2ODg1NDcjMjA2NSMyMDIwLTA0LTI0VDE5OjAwOjAwWiMyMDIwLTA0LTI0VDIwOjAwOjAwWiM0LjUjMjAyMC0wNC0yM1QyMzowMTowMFoj",
					"start": "2020-04-24T19:00:00.000Z",
					"end": "2020-04-24T20:00:00.000Z",
					"expiry": "2020-04-23T23:01:00Z",
					"charge": 4.5,
					"status": "Unavailable",
					"group": 1,
					"locationId": "2065-57688547"
				}, {
					"slotId": "IzIwNjUtNTc2ODg1NDcjMjA2NSMyMDIwLTA0LTI0VDIwOjAwOjAwWiMyMDIwLTA0LTI0VDIxOjAwOjAwWiMzLjUjMjAyMC0wNC0yM1QyMzowMTowMFoj",
					"start": "2020-04-24T20:00:00.000Z",
					"end": "2020-04-24T21:00:00.000Z",
					"expiry": "2020-04-23T23:01:00Z",
					"charge": 3.5,
					"status": "Unavailable",
					"group": 1,
					"locationId": "2065-57688547"
				}, {
					"slotId": "IzIwNjUtNTc2ODg1NDcjMjA2NSMyMDIwLTA0LTI0VDIxOjAwOjAwWiMyMDIwLTA0LTI0VDIyOjAwOjAwWiMzIzIwMjAtMDQtMjNUMjM6MDE6MDBaIw==",
					"start": "2020-04-24T21:00:00.000Z",
					"end": "2020-04-24T22:00:00.000Z",
					"expiry": "2020-04-23T23:01:00Z",
					"charge": 3,
					"status": "Unavailable",
					"group": 1,
					"locationId": "2065-57688547"
				}, {
					"slotId": "IzIwNjUtNTc2ODg1NDcjMjA2NSMyMDIwLTA0LTI1VDA3OjAwOjAwWiMyMDIwLTA0LTI1VDA4OjAwOjAwWiM3IzIwMjAtMDQtMjRUMjM6MDE6MDBaIw==",
					"start": "2020-04-25T07:00:00.000Z",
					"end": "2020-04-25T08:00:00.000Z",
					"expiry": "2020-04-24T23:01:00Z",
					"charge": 7,
					"status": "Unavailable",
					"group": 1,
					"locationId": "2065-57688547"
				}, {
					"slotId": "IzIwNjUtNTc2ODg1NDcjMjA2NSMyMDIwLTA0LTI1VDA4OjAwOjAwWiMyMDIwLTA0LTI1VDA5OjAwOjAwWiM3IzIwMjAtMDQtMjRUMjM6MDE6MDBaIw==",
					"start": "2020-04-25T08:00:00.000Z",
					"end": "2020-04-25T09:00:00.000Z",
					"expiry": "2020-04-24T23:01:00Z",
					"charge": 7,
					"status": "Unavailable",
					"group": 1,
					"locationId": "2065-57688547"
				}, {
					"slotId": "IzIwNjUtNTc2ODg1NDcjMjA2NSMyMDIwLTA0LTI1VDA5OjAwOjAwWiMyMDIwLTA0LTI1VDEwOjAwOjAwWiM3IzIwMjAtMDQtMjRUMjM6MDE6MDBaIw==",
					"start": "2020-04-25T09:00:00.000Z",
					"end": "2020-04-25T10:00:00.000Z",
					"expiry": "2020-04-24T23:01:00Z",
					"charge": 7,
					"status": "Unavailable",
					"group": 1,
					"locationId": "2065-57688547"
				}, {
					"slotId": "IzIwNjUtNTc2ODg1NDcjMjA2NSMyMDIwLTA0LTI1VDEwOjAwOjAwWiMyMDIwLTA0LTI1VDExOjAwOjAwWiM3IzIwMjAtMDQtMjRUMjM6MDE6MDBaIw==",
					"start": "2020-04-25T10:00:00.000Z",
					"end": "2020-04-25T11:00:00.000Z",
					"expiry": "2020-04-24T23:01:00Z",
					"charge": 7,
					"status": "Unavailable",
					"group": 1,
					"locationId": "2065-57688547"
				}, {
					"slotId": "IzIwNjUtNTc2ODg1NDcjMjA2NSMyMDIwLTA0LTI1VDExOjAwOjAwWiMyMDIwLTA0LTI1VDEyOjAwOjAwWiM2IzIwMjAtMDQtMjRUMjM6MDE6MDBaIw==",
					"start": "2020-04-25T11:00:00.000Z",
					"end": "2020-04-25T12:00:00.000Z",
					"expiry": "2020-04-24T23:01:00Z",
					"charge": 6,
					"status": "Unavailable",
					"group": 1,
					"locationId": "2065-57688547"
				}, {
					"slotId": "IzIwNjUtNTc2ODg1NDcjMjA2NSMyMDIwLTA0LTI1VDEyOjAwOjAwWiMyMDIwLTA0LTI1VDEzOjAwOjAwWiM2LjUjMjAyMC0wNC0yNFQyMzowMTowMFoj",
					"start": "2020-04-25T12:00:00.000Z",
					"end": "2020-04-25T13:00:00.000Z",
					"expiry": "2020-04-24T23:01:00Z",
					"charge": 6.5,
					"status": "Unavailable",
					"group": 1,
					"locationId": "2065-57688547"
				}, {
					"slotId": "IzIwNjUtNTc2ODg1NDcjMjA2NSMyMDIwLTA0LTI1VDEzOjAwOjAwWiMyMDIwLTA0LTI1VDE0OjAwOjAwWiM1LjUjMjAyMC0wNC0yNFQyMzowMTowMFoj",
					"start": "2020-04-25T13:00:00.000Z",
					"end": "2020-04-25T14:00:00.000Z",
					"expiry": "2020-04-24T23:01:00Z",
					"charge": 5.5,
					"status": "Unavailable",
					"group": 1,
					"locationId": "2065-57688547"
				}, {
					"slotId": "IzIwNjUtNTc2ODg1NDcjMjA2NSMyMDIwLTA0LTI1VDE0OjAwOjAwWiMyMDIwLTA0LTI1VDE1OjAwOjAwWiM1IzIwMjAtMDQtMjRUMjM6MDE6MDBaIw==",
					"start": "2020-04-25T14:00:00.000Z",
					"end": "2020-04-25T15:00:00.000Z",
					"expiry": "2020-04-24T23:01:00Z",
					"charge": 5,
					"status": "Unavailable",
					"group": 1,
					"locationId": "2065-57688547"
				}, {
					"slotId": "IzIwNjUtNTc2ODg1NDcjMjA2NSMyMDIwLTA0LTI1VDE1OjAwOjAwWiMyMDIwLTA0LTI1VDE2OjAwOjAwWiM0LjUjMjAyMC0wNC0yNFQyMzowMTowMFoj",
					"start": "2020-04-25T15:00:00.000Z",
					"end": "2020-04-25T16:00:00.000Z",
					"expiry": "2020-04-24T23:01:00Z",
					"charge": 4.5,
					"status": "Unavailable",
					"group": 1,
					"locationId": "2065-57688547"
				}, {
					"slotId": "IzIwNjUtNTc2ODg1NDcjMjA2NSMyMDIwLTA0LTI1VDE2OjAwOjAwWiMyMDIwLTA0LTI1VDE3OjAwOjAwWiM0LjUjMjAyMC0wNC0yNFQyMzowMTowMFoj",
					"start": "2020-04-25T16:00:00.000Z",
					"end": "2020-04-25T17:00:00.000Z",
					"expiry": "2020-04-24T23:01:00Z",
					"charge": 4.5,
					"status": "Unavailable",
					"group": 1,
					"locationId": "2065-57688547"
				}, {
					"slotId": "IzIwNjUtNTc2ODg1NDcjMjA2NSMyMDIwLTA0LTI1VDE3OjAwOjAwWiMyMDIwLTA0LTI1VDE4OjAwOjAwWiM0LjUjMjAyMC0wNC0yNFQyMzowMTowMFoj",
					"start": "2020-04-25T17:00:00.000Z",
					"end": "2020-04-25T18:00:00.000Z",
					"expiry": "2020-04-24T23:01:00Z",
					"charge": 4.5,
					"status": "Unavailable",
					"group": 1,
					"locationId": "2065-57688547"
				}, {
					"slotId": "IzIwNjUtNTc2ODg1NDcjMjA2NSMyMDIwLTA0LTI1VDE4OjAwOjAwWiMyMDIwLTA0LTI1VDE5OjAwOjAwWiM1IzIwMjAtMDQtMjRUMjM6MDE6MDBaIw==",
					"start": "2020-04-25T18:00:00.000Z",
					"end": "2020-04-25T19:00:00.000Z",
					"expiry": "2020-04-24T23:01:00Z",
					"charge": 5,
					"status": "Unavailable",
					"group": 1,
					"locationId": "2065-57688547"
				}, {
					"slotId": "IzIwNjUtNTc2ODg1NDcjMjA2NSMyMDIwLTA0LTI1VDE5OjAwOjAwWiMyMDIwLTA0LTI1VDIwOjAwOjAwWiM0IzIwMjAtMDQtMjRUMjM6MDE6MDBaIw==",
					"start": "2020-04-25T19:00:00.000Z",
					"end": "2020-04-25T20:00:00.000Z",
					"expiry": "2020-04-24T23:01:00Z",
					"charge": 4,
					"status": "Unavailable",
					"group": 1,
					"locationId": "2065-57688547"
				}, {
					"slotId": "IzIwNjUtNTc2ODg1NDcjMjA2NSMyMDIwLTA0LTI1VDIwOjAwOjAwWiMyMDIwLTA0LTI1VDIxOjAwOjAwWiM0IzIwMjAtMDQtMjRUMjM6MDE6MDBaIw==",
					"start": "2020-04-25T20:00:00.000Z",
					"end": "2020-04-25T21:00:00.000Z",
					"expiry": "2020-04-24T23:01:00Z",
					"charge": 4,
					"status": "Unavailable",
					"group": 1,
					"locationId": "2065-57688547"
				}, {
					"slotId": "2020-04-25T22:00:00+01:00#2020-04-25T23:00:00+01:00",
					"start": "2020-04-25T21:00:00.000Z",
					"end": "2020-04-25T22:00:00.000Z",
					"status": "UnAvailable"
				}, {
					"slotId": "2020-04-26T08:00:00+01:00#2020-04-26T09:00:00+01:00",
					"start": "2020-04-26T07:00:00.000Z",
					"end": "2020-04-26T08:00:00.000Z",
					"status": "UnAvailable"
				}, {
					"slotId": "2020-04-26T09:00:00+01:00#2020-04-26T10:00:00+01:00",
					"start": "2020-04-26T08:00:00.000Z",
					"end": "2020-04-26T09:00:00.000Z",
					"status": "UnAvailable"
				}, {
					"slotId": "IzIwNjUtNTc2ODg1NDcjMjA2NSMyMDIwLTA0LTI2VDA5OjAwOjAwWiMyMDIwLTA0LTI2VDEwOjAwOjAwWiM3IzIwMjAtMDQtMjVUMjM6MDE6MDBaIw==",
					"start": "2020-04-26T09:00:00.000Z",
					"end": "2020-04-26T10:00:00.000Z",
					"expiry": "2020-04-25T23:01:00Z",
					"charge": 7,
					"status": "Unavailable",
					"group": 1,
					"locationId": "2065-57688547"
				}, {
					"slotId": "IzIwNjUtNTc2ODg1NDcjMjA2NSMyMDIwLTA0LTI2VDEwOjAwOjAwWiMyMDIwLTA0LTI2VDExOjAwOjAwWiM3IzIwMjAtMDQtMjVUMjM6MDE6MDBaIw==",
					"start": "2020-04-26T10:00:00.000Z",
					"end": "2020-04-26T11:00:00.000Z",
					"expiry": "2020-04-25T23:01:00Z",
					"charge": 7,
					"status": "Unavailable",
					"group": 1,
					"locationId": "2065-57688547"
				}, {
					"slotId": "IzIwNjUtNTc2ODg1NDcjMjA2NSMyMDIwLTA0LTI2VDExOjAwOjAwWiMyMDIwLTA0LTI2VDEyOjAwOjAwWiM2IzIwMjAtMDQtMjVUMjM6MDE6MDBaIw==",
					"start": "2020-04-26T11:00:00.000Z",
					"end": "2020-04-26T12:00:00.000Z",
					"expiry": "2020-04-25T23:01:00Z",
					"charge": 6,
					"status": "Unavailable",
					"group": 1,
					"locationId": "2065-57688547"
				}, {
					"slotId": "IzIwNjUtNTc2ODg1NDcjMjA2NSMyMDIwLTA0LTI2VDEyOjAwOjAwWiMyMDIwLTA0LTI2VDEzOjAwOjAwWiM1IzIwMjAtMDQtMjVUMjM6MDE6MDBaIw==",
					"start": "2020-04-26T12:00:00.000Z",
					"end": "2020-04-26T13:00:00.000Z",
					"expiry": "2020-04-25T23:01:00Z",
					"charge": 5,
					"status": "Unavailable",
					"group": 1,
					"locationId": "2065-57688547"
				}, {
					"slotId": "IzIwNjUtNTc2ODg1NDcjMjA2NSMyMDIwLTA0LTI2VDEzOjAwOjAwWiMyMDIwLTA0LTI2VDE0OjAwOjAwWiM1LjUjMjAyMC0wNC0yNVQyMzowMTowMFoj",
					"start": "2020-04-26T13:00:00.000Z",
					"end": "2020-04-26T14:00:00.000Z",
					"expiry": "2020-04-25T23:01:00Z",
					"charge": 5.5,
					"status": "Unavailable",
					"group": 1,
					"locationId": "2065-57688547"
				}, {
					"slotId": "2020-04-26T15:00:00+01:00#2020-04-26T16:00:00+01:00",
					"start": "2020-04-26T14:00:00.000Z",
					"end": "2020-04-26T15:00:00.000Z",
					"status": "UnAvailable"
				}, {
					"slotId": "2020-04-26T16:00:00+01:00#2020-04-26T17:00:00+01:00",
					"start": "2020-04-26T15:00:00.000Z",
					"end": "2020-04-26T16:00:00.000Z",
					"status": "UnAvailable"
				}, {
					"slotId": "2020-04-26T17:00:00+01:00#2020-04-26T18:00:00+01:00",
					"start": "2020-04-26T16:00:00.000Z",
					"end": "2020-04-26T17:00:00.000Z",
					"status": "UnAvailable"
				}, {
					"slotId": "IzIwNjUtNTc2ODg1NDcjMjA2NSMyMDIwLTA0LTI2VDE3OjAwOjAwWiMyMDIwLTA0LTI2VDE4OjAwOjAwWiM2IzIwMjAtMDQtMjVUMjM6MDE6MDBaIw==",
					"start": "2020-04-26T17:00:00.000Z",
					"end": "2020-04-26T18:00:00.000Z",
					"expiry": "2020-04-25T23:01:00Z",
					"charge": 6,
					"status": "Unavailable",
					"group": 1,
					"locationId": "2065-57688547"
				}, {
					"slotId": "IzIwNjUtNTc2ODg1NDcjMjA2NSMyMDIwLTA0LTI2VDE4OjAwOjAwWiMyMDIwLTA0LTI2VDE5OjAwOjAwWiM1LjUjMjAyMC0wNC0yNVQyMzowMTowMFoj",
					"start": "2020-04-26T18:00:00.000Z",
					"end": "2020-04-26T19:00:00.000Z",
					"expiry": "2020-04-25T23:01:00Z",
					"charge": 5.5,
					"status": "Unavailable",
					"group": 1,
					"locationId": "2065-57688547"
				}, {
					"slotId": "IzIwNjUtNTc2ODg1NDcjMjA2NSMyMDIwLTA0LTI2VDE5OjAwOjAwWiMyMDIwLTA0LTI2VDIwOjAwOjAwWiM0LjUjMjAyMC0wNC0yNVQyMzowMTowMFoj",
					"start": "2020-04-26T19:00:00.000Z",
					"end": "2020-04-26T20:00:00.000Z",
					"expiry": "2020-04-25T23:01:00Z",
					"charge": 4.5,
					"status": "Unavailable",
					"group": 1,
					"locationId": "2065-57688547"
				}, {
					"slotId": "IzIwNjUtNTc2ODg1NDcjMjA2NSMyMDIwLTA0LTI2VDIwOjAwOjAwWiMyMDIwLTA0LTI2VDIxOjAwOjAwWiM0IzIwMjAtMDQtMjVUMjM6MDE6MDBaIw==",
					"start": "2020-04-26T20:00:00.000Z",
					"end": "2020-04-26T21:00:00.000Z",
					"expiry": "2020-04-25T23:01:00Z",
					"charge": 4,
					"status": "Unavailable",
					"group": 1,
					"locationId": "2065-57688547"
				}, {
					"slotId": "2020-04-26T22:00:00+01:00#2020-04-26T23:00:00+01:00",
					"start": "2020-04-26T21:00:00.000Z",
					"end": "2020-04-26T22:00:00.000Z",
					"status": "UnAvailable"
				}, {
					"slotId": "IzIwNjUtNTc2ODg1NDcjMjA2NSMyMDIwLTA0LTI3VDA3OjAwOjAwWiMyMDIwLTA0LTI3VDA4OjAwOjAwWiM2IzIwMjAtMDQtMjZUMjM6MDE6MDBaIw==",
					"start": "2020-04-27T07:00:00.000Z",
					"end": "2020-04-27T08:00:00.000Z",
					"expiry": "2020-04-26T23:01:00Z",
					"charge": 6,
					"status": "Unavailable",
					"group": 1,
					"locationId": "2065-57688547"
				}, {
					"slotId": "IzIwNjUtNTc2ODg1NDcjMjA2NSMyMDIwLTA0LTI3VDA4OjAwOjAwWiMyMDIwLTA0LTI3VDA5OjAwOjAwWiM2IzIwMjAtMDQtMjZUMjM6MDE6MDBaIw==",
					"start": "2020-04-27T08:00:00.000Z",
					"end": "2020-04-27T09:00:00.000Z",
					"expiry": "2020-04-26T23:01:00Z",
					"charge": 6,
					"status": "Unavailable",
					"group": 1,
					"locationId": "2065-57688547"
				}, {
					"slotId": "IzIwNjUtNTc2ODg1NDcjMjA2NSMyMDIwLTA0LTI3VDA5OjAwOjAwWiMyMDIwLTA0LTI3VDEwOjAwOjAwWiM1LjUjMjAyMC0wNC0yNlQyMzowMTowMFoj",
					"start": "2020-04-27T09:00:00.000Z",
					"end": "2020-04-27T10:00:00.000Z",
					"expiry": "2020-04-26T23:01:00Z",
					"charge": 5.5,
					"status": "Unavailable",
					"group": 1,
					"locationId": "2065-57688547"
				}, {
					"slotId": "IzIwNjUtNTc2ODg1NDcjMjA2NSMyMDIwLTA0LTI3VDEwOjAwOjAwWiMyMDIwLTA0LTI3VDExOjAwOjAwWiM0LjUjMjAyMC0wNC0yNlQyMzowMTowMFoj",
					"start": "2020-04-27T10:00:00.000Z",
					"end": "2020-04-27T11:00:00.000Z",
					"expiry": "2020-04-26T23:01:00Z",
					"charge": 4.5,
					"status": "Unavailable",
					"group": 1,
					"locationId": "2065-57688547"
				}, {
					"slotId": "IzIwNjUtNTc2ODg1NDcjMjA2NSMyMDIwLTA0LTI3VDExOjAwOjAwWiMyMDIwLTA0LTI3VDEyOjAwOjAwWiM0IzIwMjAtMDQtMjZUMjM6MDE6MDBaIw==",
					"start": "2020-04-27T11:00:00.000Z",
					"end": "2020-04-27T12:00:00.000Z",
					"expiry": "2020-04-26T23:01:00Z",
					"charge": 4,
					"status": "Unavailable",
					"group": 1,
					"locationId": "2065-57688547"
				}, {
					"slotId": "IzIwNjUtNTc2ODg1NDcjMjA2NSMyMDIwLTA0LTI3VDEyOjAwOjAwWiMyMDIwLTA0LTI3VDEzOjAwOjAwWiM0IzIwMjAtMDQtMjZUMjM6MDE6MDBaIw==",
					"start": "2020-04-27T12:00:00.000Z",
					"end": "2020-04-27T13:00:00.000Z",
					"expiry": "2020-04-26T23:01:00Z",
					"charge": 4,
					"status": "Unavailable",
					"group": 1,
					"locationId": "2065-57688547"
				}, {
					"slotId": "IzIwNjUtNTc2ODg1NDcjMjA2NSMyMDIwLTA0LTI3VDEzOjAwOjAwWiMyMDIwLTA0LTI3VDE0OjAwOjAwWiMzLjUjMjAyMC0wNC0yNlQyMzowMTowMFoj",
					"start": "2020-04-27T13:00:00.000Z",
					"end": "2020-04-27T14:00:00.000Z",
					"expiry": "2020-04-26T23:01:00Z",
					"charge": 3.5,
					"status": "Unavailable",
					"group": 1,
					"locationId": "2065-57688547"
				}, {
					"slotId": "IzIwNjUtNTc2ODg1NDcjMjA2NSMyMDIwLTA0LTI3VDE0OjAwOjAwWiMyMDIwLTA0LTI3VDE1OjAwOjAwWiMzLjUjMjAyMC0wNC0yNlQyMzowMTowMFoj",
					"start": "2020-04-27T14:00:00.000Z",
					"end": "2020-04-27T15:00:00.000Z",
					"expiry": "2020-04-26T23:01:00Z",
					"charge": 3.5,
					"status": "Unavailable",
					"group": 1,
					"locationId": "2065-57688547"
				}, {
					"slotId": "IzIwNjUtNTc2ODg1NDcjMjA2NSMyMDIwLTA0LTI3VDE1OjAwOjAwWiMyMDIwLTA0LTI3VDE2OjAwOjAwWiMzLjUjMjAyMC0wNC0yNlQyMzowMTowMFoj",
					"start": "2020-04-27T15:00:00.000Z",
					"end": "2020-04-27T16:00:00.000Z",
					"expiry": "2020-04-26T23:01:00Z",
					"charge": 3.5,
					"status": "Unavailable",
					"group": 1,
					"locationId": "2065-57688547"
				}, {
					"slotId": "IzIwNjUtNTc2ODg1NDcjMjA2NSMyMDIwLTA0LTI3VDE2OjAwOjAwWiMyMDIwLTA0LTI3VDE3OjAwOjAwWiM0IzIwMjAtMDQtMjZUMjM6MDE6MDBaIw==",
					"start": "2020-04-27T16:00:00.000Z",
					"end": "2020-04-27T17:00:00.000Z",
					"expiry": "2020-04-26T23:01:00Z",
					"charge": 4,
					"status": "Unavailable",
					"group": 1,
					"locationId": "2065-57688547"
				}, {
					"slotId": "IzIwNjUtNTc2ODg1NDcjMjA2NSMyMDIwLTA0LTI3VDE3OjAwOjAwWiMyMDIwLTA0LTI3VDE4OjAwOjAwWiM0IzIwMjAtMDQtMjZUMjM6MDE6MDBaIw==",
					"start": "2020-04-27T17:00:00.000Z",
					"end": "2020-04-27T18:00:00.000Z",
					"expiry": "2020-04-26T23:01:00Z",
					"charge": 4,
					"status": "Unavailable",
					"group": 1,
					"locationId": "2065-57688547"
				}, {
					"slotId": "IzIwNjUtNTc2ODg1NDcjMjA2NSMyMDIwLTA0LTI3VDE4OjAwOjAwWiMyMDIwLTA0LTI3VDE5OjAwOjAwWiM0IzIwMjAtMDQtMjZUMjM6MDE6MDBaIw==",
					"start": "2020-04-27T18:00:00.000Z",
					"end": "2020-04-27T19:00:00.000Z",
					"expiry": "2020-04-26T23:01:00Z",
					"charge": 4,
					"status": "Unavailable",
					"group": 1,
					"locationId": "2065-57688547"
				}, {
					"slotId": "IzIwNjUtNTc2ODg1NDcjMjA2NSMyMDIwLTA0LTI3VDE5OjAwOjAwWiMyMDIwLTA0LTI3VDIwOjAwOjAwWiMzLjUjMjAyMC0wNC0yNlQyMzowMTowMFoj",
					"start": "2020-04-27T19:00:00.000Z",
					"end": "2020-04-27T20:00:00.000Z",
					"expiry": "2020-04-26T23:01:00Z",
					"charge": 3.5,
					"status": "Unavailable",
					"group": 1,
					"locationId": "2065-57688547"
				}, {
					"slotId": "IzIwNjUtNTc2ODg1NDcjMjA2NSMyMDIwLTA0LTI3VDIwOjAwOjAwWiMyMDIwLTA0LTI3VDIxOjAwOjAwWiMyLjUjMjAyMC0wNC0yNlQyMzowMTowMFoj",
					"start": "2020-04-27T20:00:00.000Z",
					"end": "2020-04-27T21:00:00.000Z",
					"expiry": "2020-04-26T23:01:00Z",
					"charge": 2.5,
					"status": "Unavailable",
					"group": 1,
					"locationId": "2065-57688547"
				}, {
					"slotId": "IzIwNjUtNTc2ODg1NDcjMjA2NSMyMDIwLTA0LTI3VDIxOjAwOjAwWiMyMDIwLTA0LTI3VDIyOjAwOjAwWiMyIzIwMjAtMDQtMjZUMjM6MDE6MDBaIw==",
					"start": "2020-04-27T21:00:00.000Z",
					"end": "2020-04-27T22:00:00.000Z",
					"expiry": "2020-04-26T23:01:00Z",
					"charge": 2,
					"status": "Unavailable",
					"group": 1,
					"locationId": "2065-57688547"
				}],
				"startDate": "2020-04-07T08:13:07.912Z",
				"selectedDate": "2020-04-21T00:00:00.000Z",
				"weekLimit": 3,
				"slotGroup": 1,
				"shoppingMethod": "delivery",
				"storeId": "2065"
			},
			"params": {},
			"hash": "337942041054467"
		}
	},
	"shoppingMethod": "delivery",
	"trolley": {
		"basketId": "825479033_2065",
		"storeId": "2065",
		"orderNo": "825479033",
		"guidePrice": 2.3,
		"savings": 0,
		"staffDiscount": null,
		"totalItems": 3,
		"constraints": {
			"maxItemCount": 80
		},
		"issues": null,
		"shoppingMethod": "delivery",
		"isAmendBasket": false,
		"IsBagless": true,
		"amendExpiry": null,
		"amendOrderId": null,
		"canExtendSlot": true,
		"deliveryAddress": {
			"name": "Home",
			"addressId": "57688547",
			"addressLine1": null,
			"isBusinessAddress": false,
			"isBlockedAddress": false
		},
		"collectionLocation": {
			"postcode": "CB249LJ"
		},
		"deliveryPreferences": {
			"deliveryInstruction": "",
			"isBagless": true,
			"mobilePhone": "07843203594",
			"dayPhone": "07843203594",
			"eveningPhone": "07843203594"
		},
		"customerPreferences": {
			"substituteAllItems": true
		},
		"slot": null,
		"previousSlot": null,
		"charges": {
			"surcharge": 4,
			"minimumBasketValue": 40,
			"bagCharge": 0.4
		},
		"subscription": {
			"planName": "Any day 6-Month",
			"planId": 34,
			"planType": "anytime",
			"planDurationInMonths": 6,
			"applicableDays": [1, 2, 3, 4, 5, 6, 7],
			"status": "Active",
			"valid": true,
			"basketvalue": "0.00",
			"freeSameDayDelivery": false,
			"isTrialPlan": false
		},
		"promotions": [],
		"availableShoppingMethods": ["delivery", "collection"],
		"items": [{
			"quantity": 1,
			"cost": 0.55,
			"weight": 0,
			"originalQuantity": 0,
			"originalWeight": 0,
			"isNewlyAdded": true,
			"substitutionOption": "FindSuitableAlternative",
			"pickerNote": "",
			"customerUnitChoice": "pcs",
			"itemLimitReached": false,
			"groupLimitReached": false,
			"groupBulkBuyQuantity": 1,
			"product": {
				"id": "254878476",
				"aisleId": "b;Rm9vZCUyMEN1cGJvYXJkJTdDRHJpZWQlMjBQYXN0YSwlMjBSaWNlLCUyME5vb2RsZXMlMjAmJTIwQ291cyUyMENvdXMlN0NQYXN0YSUyMCYlMjBTcGFnaGV0dGk=",
				"aisleName": "Pasta & Spaghetti",
				"shelfId": "b;Rm9vZCUyMEN1cGJvYXJkJTdDRHJpZWQlMjBQYXN0YSwlMjBSaWNlLCUyME5vb2RsZXMlMjAmJTIwQ291cyUyMENvdXMlN0NQYXN0YSUyMCYlMjBTcGFnaGV0dGklN0NQYXN0YSUyMFNoYXBlcw==",
				"shelfName": "Pasta Shapes",
				"baseProductId": "50687061",
				"title": "Tesco Farfalle Pasta Bows 500G",
				"brandName": "Tesco",
				"shortDescription": null,
				"defaultImageUrl": "https://img.tesco.com/Groceries/pi/102/5000119300102/IDShot_225x225.jpg",
				"departmentName": "Dried Pasta, Rice, Noodles & Cous Cous",
				"displayType": "Quantity",
				"productType": "SingleProduct",
				"averageWeight": null,
				"bulkBuyLimit": 3,
				"groupBulkBuyLimit": 0,
				"bulkBuyLimitMessage": "You are able to order a maximum of 3 of this item",
				"bulkBuyLimitGroupId": "G00030670",
				"timeRestrictedDelivery": null,
				"restrictedDelivery": null,
				"isForSale": true,
				"isInFavourites": true,
				"isRestrictedOrderAmendment": null,
				"status": "AvailableForSale",
				"maxWeight": 0,
				"minWeight": 0,
				"increment": 0,
				"catchWeightList": null,
				"restrictions": [],
				"price": 0.55,
				"unitPrice": 1.1,
				"unitOfMeasure": "kg",
				"substitutions": []
			},
			"promotions": []
		}, {
			"quantity": 1,
			"cost": 0.85,
			"weight": 0,
			"originalQuantity": 0,
			"originalWeight": 0,
			"isNewlyAdded": true,
			"substitutionOption": "FindSuitableAlternative",
			"pickerNote": "",
			"customerUnitChoice": "pcs",
			"itemLimitReached": false,
			"groupLimitReached": false,
			"groupBulkBuyQuantity": 1,
			"product": {
				"id": "302872830",
				"aisleId": "b;RnJvemVuJTIwRm9vZCU3Q0ljZSUyMENyZWFtLCUyMEljZSUyMExvbGxpZXMlMjAmJTIwRnJvemVuJTIwRGVzc2VydHMlN0NJY2UlMjBMb2xsaWVz",
				"aisleName": "Ice Lollies",
				"shelfId": "b;RnJvemVuJTIwRm9vZCU3Q0ljZSUyMENyZWFtLCUyMEljZSUyMExvbGxpZXMlMjAmJTIwRnJvemVuJTIwRGVzc2VydHMlN0NJY2UlMjBMb2xsaWVzJTdDSWNlJTIwTG9sbGllcw==",
				"shelfName": "Ice Lollies",
				"baseProductId": "86278283",
				"title": "Ms. Molly's Assorted Fruit Lollies 8X35ml",
				"brandName": "Ms Mollys",
				"shortDescription": null,
				"defaultImageUrl": "https://img.tesco.com/Groceries/pi/251/5057967137251/IDShot_225x225.jpg",
				"departmentName": "Ice Cream, Ice Lollies & Frozen Desserts",
				"displayType": "Quantity",
				"productType": "SingleProduct",
				"averageWeight": null,
				"bulkBuyLimit": 99,
				"groupBulkBuyLimit": 0,
				"bulkBuyLimitMessage": "Sorry, there is a limit of 99 on this product",
				"bulkBuyLimitGroupId": null,
				"timeRestrictedDelivery": null,
				"restrictedDelivery": null,
				"isForSale": true,
				"isInFavourites": false,
				"isRestrictedOrderAmendment": null,
				"status": "AvailableForSale",
				"maxWeight": 0,
				"minWeight": 0,
				"increment": 0,
				"catchWeightList": null,
				"restrictions": [],
				"price": 0.85,
				"unitPrice": 0.304,
				"unitOfMeasure": "100ml",
				"substitutions": []
			},
			"promotions": []
		}, {
			"quantity": 1,
			"cost": 0.9,
			"weight": 0,
			"originalQuantity": 0,
			"originalWeight": 0,
			"isNewlyAdded": true,
			"substitutionOption": "FindSuitableAlternative",
			"pickerNote": "",
			"customerUnitChoice": "pcs",
			"itemLimitReached": false,
			"groupLimitReached": false,
			"groupBulkBuyQuantity": 1,
			"product": {
				"id": "285212132",
				"aisleId": "b;RnJlc2glMjBGb29kJTdDRnJlc2glMjBTYWxhZCUyMCYlMjBEaXBzJTdDVG9tYXRvZXM=",
				"aisleName": "Tomatoes",
				"shelfId": "b;RnJlc2glMjBGb29kJTdDRnJlc2glMjBTYWxhZCUyMCYlMjBEaXBzJTdDVG9tYXRvZXMlN0NCYWJ5JTIwJiUyMENoZXJyeSUyMFRvbWF0b2Vz",
				"shelfName": "Baby & Cherry Tomatoes",
				"baseProductId": "77454543",
				"title": "Tesco Cherry Tomatoes 330G",
				"brandName": "Tesco",
				"shortDescription": null,
				"defaultImageUrl": "https://img.tesco.com/Groceries/pi/534/0000010032534/IDShot_225x225.jpg",
				"departmentName": "Fresh Salad & Dips",
				"displayType": "Quantity",
				"productType": "SingleProduct",
				"averageWeight": null,
				"bulkBuyLimit": 99,
				"groupBulkBuyLimit": 0,
				"bulkBuyLimitMessage": "Sorry, there is a limit of 99 on this product",
				"bulkBuyLimitGroupId": null,
				"timeRestrictedDelivery": null,
				"restrictedDelivery": null,
				"isForSale": true,
				"isInFavourites": true,
				"isRestrictedOrderAmendment": null,
				"status": "AvailableForSale",
				"maxWeight": 0,
				"minWeight": 0,
				"increment": 0,
				"catchWeightList": null,
				"restrictions": [],
				"price": 0.9,
				"unitPrice": 2.73,
				"unitOfMeasure": "kg",
				"substitutions": []
			},
			"promotions": []
		}]
	},
	"locations": [],
	"storeId": "2065",
	"slots": [{
		"slotId": "IzIwNjUtNTc2ODg1NDcjMjA2NSMyMDIwLTA0LTIxVDA3OjAwOjAwWiMyMDIwLTA0LTIxVDA4OjAwOjAwWiM2IzIwMjAtMDQtMjBUMjM6MDE6MDBaIw==",
		"start": "2020-04-21T07:00:00.000Z",
		"end": "2020-04-21T08:00:00.000Z",
		"expiry": "2020-04-20T23:01:00Z",
		"charge": 6,
		"status": "Unavailable",
		"group": 1,
		"locationId": "2065-57688547"
	}, {
		"slotId": "IzIwNjUtNTc2ODg1NDcjMjA2NSMyMDIwLTA0LTIxVDA4OjAwOjAwWiMyMDIwLTA0LTIxVDA5OjAwOjAwWiM2IzIwMjAtMDQtMjBUMjM6MDE6MDBaIw==",
		"start": "2020-04-21T08:00:00.000Z",
		"end": "2020-04-21T09:00:00.000Z",
		"expiry": "2020-04-20T23:01:00Z",
		"charge": 6,
		"status": "Unavailable",
		"group": 1,
		"locationId": "2065-57688547"
	}, {
		"slotId": "IzIwNjUtNTc2ODg1NDcjMjA2NSMyMDIwLTA0LTIxVDA5OjAwOjAwWiMyMDIwLTA0LTIxVDEwOjAwOjAwWiM2IzIwMjAtMDQtMjBUMjM6MDE6MDBaIw==",
		"start": "2020-04-21T09:00:00.000Z",
		"end": "2020-04-21T10:00:00.000Z",
		"expiry": "2020-04-20T23:01:00Z",
		"charge": 6,
		"status": "Unavailable",
		"group": 1,
		"locationId": "2065-57688547"
	}, {
		"slotId": "IzIwNjUtNTc2ODg1NDcjMjA2NSMyMDIwLTA0LTIxVDEwOjAwOjAwWiMyMDIwLTA0LTIxVDExOjAwOjAwWiM1IzIwMjAtMDQtMjBUMjM6MDE6MDBaIw==",
		"start": "2020-04-21T10:00:00.000Z",
		"end": "2020-04-21T11:00:00.000Z",
		"expiry": "2020-04-20T23:01:00Z",
		"charge": 5,
		"status": "Unavailable",
		"group": 1,
		"locationId": "2065-57688547"
	}, {
		"slotId": "IzIwNjUtNTc2ODg1NDcjMjA2NSMyMDIwLTA0LTIxVDExOjAwOjAwWiMyMDIwLTA0LTIxVDEyOjAwOjAwWiM0IzIwMjAtMDQtMjBUMjM6MDE6MDBaIw==",
		"start": "2020-04-21T11:00:00.000Z",
		"end": "2020-04-21T12:00:00.000Z",
		"expiry": "2020-04-20T23:01:00Z",
		"charge": 4,
		"status": "Unavailable",
		"group": 1,
		"locationId": "2065-57688547"
	}, {
		"slotId": "IzIwNjUtNTc2ODg1NDcjMjA2NSMyMDIwLTA0LTIxVDEyOjAwOjAwWiMyMDIwLTA0LTIxVDEzOjAwOjAwWiM0IzIwMjAtMDQtMjBUMjM6MDE6MDBaIw==",
		"start": "2020-04-21T12:00:00.000Z",
		"end": "2020-04-21T13:00:00.000Z",
		"expiry": "2020-04-20T23:01:00Z",
		"charge": 4,
		"status": "Unavailable",
		"group": 1,
		"locationId": "2065-57688547"
	}, {
		"slotId": "IzIwNjUtNTc2ODg1NDcjMjA2NSMyMDIwLTA0LTIxVDEzOjAwOjAwWiMyMDIwLTA0LTIxVDE0OjAwOjAwWiMzLjUjMjAyMC0wNC0yMFQyMzowMTowMFoj",
		"start": "2020-04-21T13:00:00.000Z",
		"end": "2020-04-21T14:00:00.000Z",
		"expiry": "2020-04-20T23:01:00Z",
		"charge": 3.5,
		"status": "Unavailable",
		"group": 1,
		"locationId": "2065-57688547"
	}, {
		"slotId": "IzIwNjUtNTc2ODg1NDcjMjA2NSMyMDIwLTA0LTIxVDE0OjAwOjAwWiMyMDIwLTA0LTIxVDE1OjAwOjAwWiMzLjUjMjAyMC0wNC0yMFQyMzowMTowMFoj",
		"start": "2020-04-21T14:00:00.000Z",
		"end": "2020-04-21T15:00:00.000Z",
		"expiry": "2020-04-20T23:01:00Z",
		"charge": 3.5,
		"status": "Unavailable",
		"group": 1,
		"locationId": "2065-57688547"
	}, {
		"slotId": "IzIwNjUtNTc2ODg1NDcjMjA2NSMyMDIwLTA0LTIxVDE1OjAwOjAwWiMyMDIwLTA0LTIxVDE2OjAwOjAwWiMzIzIwMjAtMDQtMjBUMjM6MDE6MDBaIw==",
		"start": "2020-04-21T15:00:00.000Z",
		"end": "2020-04-21T16:00:00.000Z",
		"expiry": "2020-04-20T23:01:00Z",
		"charge": 3,
		"status": "Unavailable",
		"group": 1,
		"locationId": "2065-57688547"
	}, {
		"slotId": "IzIwNjUtNTc2ODg1NDcjMjA2NSMyMDIwLTA0LTIxVDE2OjAwOjAwWiMyMDIwLTA0LTIxVDE3OjAwOjAwWiMzLjUjMjAyMC0wNC0yMFQyMzowMTowMFoj",
		"start": "2020-04-21T16:00:00.000Z",
		"end": "2020-04-21T17:00:00.000Z",
		"expiry": "2020-04-20T23:01:00Z",
		"charge": 3.5,
		"status": "Unavailable",
		"group": 1,
		"locationId": "2065-57688547"
	}, {
		"slotId": "IzIwNjUtNTc2ODg1NDcjMjA2NSMyMDIwLTA0LTIxVDE3OjAwOjAwWiMyMDIwLTA0LTIxVDE4OjAwOjAwWiMzIzIwMjAtMDQtMjBUMjM6MDE6MDBaIw==",
		"start": "2020-04-21T17:00:00.000Z",
		"end": "2020-04-21T18:00:00.000Z",
		"expiry": "2020-04-20T23:01:00Z",
		"charge": 3,
		"status": "Unavailable",
		"group": 1,
		"locationId": "2065-57688547"
	}, {
		"slotId": "IzIwNjUtNTc2ODg1NDcjMjA2NSMyMDIwLTA0LTIxVDE4OjAwOjAwWiMyMDIwLTA0LTIxVDE5OjAwOjAwWiMzLjUjMjAyMC0wNC0yMFQyMzowMTowMFoj",
		"start": "2020-04-21T18:00:00.000Z",
		"end": "2020-04-21T19:00:00.000Z",
		"expiry": "2020-04-20T23:01:00Z",
		"charge": 3.5,
		"status": "Unavailable",
		"group": 1,
		"locationId": "2065-57688547"
	}, {
		"slotId": "IzIwNjUtNTc2ODg1NDcjMjA2NSMyMDIwLTA0LTIxVDE5OjAwOjAwWiMyMDIwLTA0LTIxVDIwOjAwOjAwWiMyLjUjMjAyMC0wNC0yMFQyMzowMTowMFoj",
		"start": "2020-04-21T19:00:00.000Z",
		"end": "2020-04-21T20:00:00.000Z",
		"expiry": "2020-04-20T23:01:00Z",
		"charge": 2.5,
		"status": "Unavailable",
		"group": 1,
		"locationId": "2065-57688547"
	}, {
		"slotId": "IzIwNjUtNTc2ODg1NDcjMjA2NSMyMDIwLTA0LTIxVDIwOjAwOjAwWiMyMDIwLTA0LTIxVDIxOjAwOjAwWiMyIzIwMjAtMDQtMjBUMjM6MDE6MDBaIw==",
		"start": "2020-04-21T20:00:00.000Z",
		"end": "2020-04-21T21:00:00.000Z",
		"expiry": "2020-04-20T23:01:00Z",
		"charge": 2,
		"status": "Unavailable",
		"group": 1,
		"locationId": "2065-57688547"
	}, {
		"slotId": "IzIwNjUtNTc2ODg1NDcjMjA2NSMyMDIwLTA0LTIxVDIxOjAwOjAwWiMyMDIwLTA0LTIxVDIyOjAwOjAwWiMyIzIwMjAtMDQtMjBUMjM6MDE6MDBaIw==",
		"start": "2020-04-21T21:00:00.000Z",
		"end": "2020-04-21T22:00:00.000Z",
		"expiry": "2020-04-20T23:01:00Z",
		"charge": 2,
		"status": "Unavailable",
		"group": 1,
		"locationId": "2065-57688547"
	}, {
		"slotId": "IzIwNjUtNTc2ODg1NDcjMjA2NSMyMDIwLTA0LTIyVDA3OjAwOjAwWiMyMDIwLTA0LTIyVDA4OjAwOjAwWiM0LjUjMjAyMC0wNC0yMVQyMzowMTowMFoj",
		"start": "2020-04-22T07:00:00.000Z",
		"end": "2020-04-22T08:00:00.000Z",
		"expiry": "2020-04-21T23:01:00Z",
		"charge": 4.5,
		"status": "Unavailable",
		"group": 1,
		"locationId": "2065-57688547"
	}, {
		"slotId": "IzIwNjUtNTc2ODg1NDcjMjA2NSMyMDIwLTA0LTIyVDA4OjAwOjAwWiMyMDIwLTA0LTIyVDA5OjAwOjAwWiM0IzIwMjAtMDQtMjFUMjM6MDE6MDBaIw==",
		"start": "2020-04-22T08:00:00.000Z",
		"end": "2020-04-22T09:00:00.000Z",
		"expiry": "2020-04-21T23:01:00Z",
		"charge": 4,
		"status": "Unavailable",
		"group": 1,
		"locationId": "2065-57688547"
	}, {
		"slotId": "IzIwNjUtNTc2ODg1NDcjMjA2NSMyMDIwLTA0LTIyVDA5OjAwOjAwWiMyMDIwLTA0LTIyVDEwOjAwOjAwWiMzIzIwMjAtMDQtMjFUMjM6MDE6MDBaIw==",
		"start": "2020-04-22T09:00:00.000Z",
		"end": "2020-04-22T10:00:00.000Z",
		"expiry": "2020-04-21T23:01:00Z",
		"charge": 3,
		"status": "Unavailable",
		"group": 1,
		"locationId": "2065-57688547"
	}, {
		"slotId": "IzIwNjUtNTc2ODg1NDcjMjA2NSMyMDIwLTA0LTIyVDEwOjAwOjAwWiMyMDIwLTA0LTIyVDExOjAwOjAwWiMzIzIwMjAtMDQtMjFUMjM6MDE6MDBaIw==",
		"start": "2020-04-22T10:00:00.000Z",
		"end": "2020-04-22T11:00:00.000Z",
		"expiry": "2020-04-21T23:01:00Z",
		"charge": 3,
		"status": "Unavailable",
		"group": 1,
		"locationId": "2065-57688547"
	}, {
		"slotId": "IzIwNjUtNTc2ODg1NDcjMjA2NSMyMDIwLTA0LTIyVDExOjAwOjAwWiMyMDIwLTA0LTIyVDEyOjAwOjAwWiMyLjUjMjAyMC0wNC0yMVQyMzowMTowMFoj",
		"start": "2020-04-22T11:00:00.000Z",
		"end": "2020-04-22T12:00:00.000Z",
		"expiry": "2020-04-21T23:01:00Z",
		"charge": 2.5,
		"status": "Unavailable",
		"group": 1,
		"locationId": "2065-57688547"
	}, {
		"slotId": "IzIwNjUtNTc2ODg1NDcjMjA2NSMyMDIwLTA0LTIyVDEyOjAwOjAwWiMyMDIwLTA0LTIyVDEzOjAwOjAwWiMyIzIwMjAtMDQtMjFUMjM6MDE6MDBaIw==",
		"start": "2020-04-22T12:00:00.000Z",
		"end": "2020-04-22T13:00:00.000Z",
		"expiry": "2020-04-21T23:01:00Z",
		"charge": 2,
		"status": "Unavailable",
		"group": 1,
		"locationId": "2065-57688547"
	}, {
		"slotId": "IzIwNjUtNTc2ODg1NDcjMjA2NSMyMDIwLTA0LTIyVDEzOjAwOjAwWiMyMDIwLTA0LTIyVDE0OjAwOjAwWiMyLjUjMjAyMC0wNC0yMVQyMzowMTowMFoj",
		"start": "2020-04-22T13:00:00.000Z",
		"end": "2020-04-22T14:00:00.000Z",
		"expiry": "2020-04-21T23:01:00Z",
		"charge": 2.5,
		"status": "Unavailable",
		"group": 1,
		"locationId": "2065-57688547"
	}, {
		"slotId": "IzIwNjUtNTc2ODg1NDcjMjA2NSMyMDIwLTA0LTIyVDE0OjAwOjAwWiMyMDIwLTA0LTIyVDE1OjAwOjAwWiMyIzIwMjAtMDQtMjFUMjM6MDE6MDBaIw==",
		"start": "2020-04-22T14:00:00.000Z",
		"end": "2020-04-22T15:00:00.000Z",
		"expiry": "2020-04-21T23:01:00Z",
		"charge": 2,
		"status": "Unavailable",
		"group": 1,
		"locationId": "2065-57688547"
	}, {
		"slotId": "IzIwNjUtNTc2ODg1NDcjMjA2NSMyMDIwLTA0LTIyVDE1OjAwOjAwWiMyMDIwLTA0LTIyVDE2OjAwOjAwWiMyIzIwMjAtMDQtMjFUMjM6MDE6MDBaIw==",
		"start": "2020-04-22T15:00:00.000Z",
		"end": "2020-04-22T16:00:00.000Z",
		"expiry": "2020-04-21T23:01:00Z",
		"charge": 2,
		"status": "Unavailable",
		"group": 1,
		"locationId": "2065-57688547"
	}, {
		"slotId": "IzIwNjUtNTc2ODg1NDcjMjA2NSMyMDIwLTA0LTIyVDE2OjAwOjAwWiMyMDIwLTA0LTIyVDE3OjAwOjAwWiMyLjUjMjAyMC0wNC0yMVQyMzowMTowMFoj",
		"start": "2020-04-22T16:00:00.000Z",
		"end": "2020-04-22T17:00:00.000Z",
		"expiry": "2020-04-21T23:01:00Z",
		"charge": 2.5,
		"status": "Unavailable",
		"group": 1,
		"locationId": "2065-57688547"
	}, {
		"slotId": "IzIwNjUtNTc2ODg1NDcjMjA2NSMyMDIwLTA0LTIyVDE3OjAwOjAwWiMyMDIwLTA0LTIyVDE4OjAwOjAwWiMyIzIwMjAtMDQtMjFUMjM6MDE6MDBaIw==",
		"start": "2020-04-22T17:00:00.000Z",
		"end": "2020-04-22T18:00:00.000Z",
		"expiry": "2020-04-21T23:01:00Z",
		"charge": 2,
		"status": "Unavailable",
		"group": 1,
		"locationId": "2065-57688547"
	}, {
		"slotId": "IzIwNjUtNTc2ODg1NDcjMjA2NSMyMDIwLTA0LTIyVDE4OjAwOjAwWiMyMDIwLTA0LTIyVDE5OjAwOjAwWiMyIzIwMjAtMDQtMjFUMjM6MDE6MDBaIw==",
		"start": "2020-04-22T18:00:00.000Z",
		"end": "2020-04-22T19:00:00.000Z",
		"expiry": "2020-04-21T23:01:00Z",
		"charge": 2,
		"status": "Unavailable",
		"group": 1,
		"locationId": "2065-57688547"
	}, {
		"slotId": "IzIwNjUtNTc2ODg1NDcjMjA2NSMyMDIwLTA0LTIyVDE5OjAwOjAwWiMyMDIwLTA0LTIyVDIwOjAwOjAwWiMyIzIwMjAtMDQtMjFUMjM6MDE6MDBaIw==",
		"start": "2020-04-22T19:00:00.000Z",
		"end": "2020-04-22T20:00:00.000Z",
		"expiry": "2020-04-21T23:01:00Z",
		"charge": 2,
		"status": "Unavailable",
		"group": 1,
		"locationId": "2065-57688547"
	}, {
		"slotId": "IzIwNjUtNTc2ODg1NDcjMjA2NSMyMDIwLTA0LTIyVDIwOjAwOjAwWiMyMDIwLTA0LTIyVDIxOjAwOjAwWiMyIzIwMjAtMDQtMjFUMjM6MDE6MDBaIw==",
		"start": "2020-04-22T20:00:00.000Z",
		"end": "2020-04-22T21:00:00.000Z",
		"expiry": "2020-04-21T23:01:00Z",
		"charge": 2,
		"status": "Unavailable",
		"group": 1,
		"locationId": "2065-57688547"
	}, {
		"slotId": "IzIwNjUtNTc2ODg1NDcjMjA2NSMyMDIwLTA0LTIyVDIxOjAwOjAwWiMyMDIwLTA0LTIyVDIyOjAwOjAwWiMyIzIwMjAtMDQtMjFUMjM6MDE6MDBaIw==",
		"start": "2020-04-22T21:00:00.000Z",
		"end": "2020-04-22T22:00:00.000Z",
		"expiry": "2020-04-21T23:01:00Z",
		"charge": 2,
		"status": "Unavailable",
		"group": 1,
		"locationId": "2065-57688547"
	}, {
		"slotId": "IzIwNjUtNTc2ODg1NDcjMjA2NSMyMDIwLTA0LTIzVDA3OjAwOjAwWiMyMDIwLTA0LTIzVDA4OjAwOjAwWiM2IzIwMjAtMDQtMjJUMjM6MDE6MDBaIw==",
		"start": "2020-04-23T07:00:00.000Z",
		"end": "2020-04-23T08:00:00.000Z",
		"expiry": "2020-04-22T23:01:00Z",
		"charge": 6,
		"status": "Unavailable",
		"group": 1,
		"locationId": "2065-57688547"
	}, {
		"slotId": "IzIwNjUtNTc2ODg1NDcjMjA2NSMyMDIwLTA0LTIzVDA4OjAwOjAwWiMyMDIwLTA0LTIzVDA5OjAwOjAwWiM2IzIwMjAtMDQtMjJUMjM6MDE6MDBaIw==",
		"start": "2020-04-23T08:00:00.000Z",
		"end": "2020-04-23T09:00:00.000Z",
		"expiry": "2020-04-22T23:01:00Z",
		"charge": 6,
		"status": "Unavailable",
		"group": 1,
		"locationId": "2065-57688547"
	}, {
		"slotId": "IzIwNjUtNTc2ODg1NDcjMjA2NSMyMDIwLTA0LTIzVDA5OjAwOjAwWiMyMDIwLTA0LTIzVDEwOjAwOjAwWiM2IzIwMjAtMDQtMjJUMjM6MDE6MDBaIw==",
		"start": "2020-04-23T09:00:00.000Z",
		"end": "2020-04-23T10:00:00.000Z",
		"expiry": "2020-04-22T23:01:00Z",
		"charge": 6,
		"status": "Unavailable",
		"group": 1,
		"locationId": "2065-57688547"
	}, {
		"slotId": "IzIwNjUtNTc2ODg1NDcjMjA2NSMyMDIwLTA0LTIzVDEwOjAwOjAwWiMyMDIwLTA0LTIzVDExOjAwOjAwWiM1IzIwMjAtMDQtMjJUMjM6MDE6MDBaIw==",
		"start": "2020-04-23T10:00:00.000Z",
		"end": "2020-04-23T11:00:00.000Z",
		"expiry": "2020-04-22T23:01:00Z",
		"charge": 5,
		"status": "Unavailable",
		"group": 1,
		"locationId": "2065-57688547"
	}, {
		"slotId": "IzIwNjUtNTc2ODg1NDcjMjA2NSMyMDIwLTA0LTIzVDExOjAwOjAwWiMyMDIwLTA0LTIzVDEyOjAwOjAwWiM0LjUjMjAyMC0wNC0yMlQyMzowMTowMFoj",
		"start": "2020-04-23T11:00:00.000Z",
		"end": "2020-04-23T12:00:00.000Z",
		"expiry": "2020-04-22T23:01:00Z",
		"charge": 4.5,
		"status": "Unavailable",
		"group": 1,
		"locationId": "2065-57688547"
	}, {
		"slotId": "IzIwNjUtNTc2ODg1NDcjMjA2NSMyMDIwLTA0LTIzVDEyOjAwOjAwWiMyMDIwLTA0LTIzVDEzOjAwOjAwWiM1IzIwMjAtMDQtMjJUMjM6MDE6MDBaIw==",
		"start": "2020-04-23T12:00:00.000Z",
		"end": "2020-04-23T13:00:00.000Z",
		"expiry": "2020-04-22T23:01:00Z",
		"charge": 5,
		"status": "Unavailable",
		"group": 1,
		"locationId": "2065-57688547"
	}, {
		"slotId": "IzIwNjUtNTc2ODg1NDcjMjA2NSMyMDIwLTA0LTIzVDEzOjAwOjAwWiMyMDIwLTA0LTIzVDE0OjAwOjAwWiM0IzIwMjAtMDQtMjJUMjM6MDE6MDBaIw==",
		"start": "2020-04-23T13:00:00.000Z",
		"end": "2020-04-23T14:00:00.000Z",
		"expiry": "2020-04-22T23:01:00Z",
		"charge": 4,
		"status": "Unavailable",
		"group": 1,
		"locationId": "2065-57688547"
	}, {
		"slotId": "IzIwNjUtNTc2ODg1NDcjMjA2NSMyMDIwLTA0LTIzVDE0OjAwOjAwWiMyMDIwLTA0LTIzVDE1OjAwOjAwWiMzLjUjMjAyMC0wNC0yMlQyMzowMTowMFoj",
		"start": "2020-04-23T14:00:00.000Z",
		"end": "2020-04-23T15:00:00.000Z",
		"expiry": "2020-04-22T23:01:00Z",
		"charge": 3.5,
		"status": "Unavailable",
		"group": 1,
		"locationId": "2065-57688547"
	}, {
		"slotId": "IzIwNjUtNTc2ODg1NDcjMjA2NSMyMDIwLTA0LTIzVDE1OjAwOjAwWiMyMDIwLTA0LTIzVDE2OjAwOjAwWiM0LjUjMjAyMC0wNC0yMlQyMzowMTowMFoj",
		"start": "2020-04-23T15:00:00.000Z",
		"end": "2020-04-23T16:00:00.000Z",
		"expiry": "2020-04-22T23:01:00Z",
		"charge": 4.5,
		"status": "Unavailable",
		"group": 1,
		"locationId": "2065-57688547"
	}, {
		"slotId": "IzIwNjUtNTc2ODg1NDcjMjA2NSMyMDIwLTA0LTIzVDE2OjAwOjAwWiMyMDIwLTA0LTIzVDE3OjAwOjAwWiM0LjUjMjAyMC0wNC0yMlQyMzowMTowMFoj",
		"start": "2020-04-23T16:00:00.000Z",
		"end": "2020-04-23T17:00:00.000Z",
		"expiry": "2020-04-22T23:01:00Z",
		"charge": 4.5,
		"status": "Unavailable",
		"group": 1,
		"locationId": "2065-57688547"
	}, {
		"slotId": "IzIwNjUtNTc2ODg1NDcjMjA2NSMyMDIwLTA0LTIzVDE3OjAwOjAwWiMyMDIwLTA0LTIzVDE4OjAwOjAwWiM0IzIwMjAtMDQtMjJUMjM6MDE6MDBaIw==",
		"start": "2020-04-23T17:00:00.000Z",
		"end": "2020-04-23T18:00:00.000Z",
		"expiry": "2020-04-22T23:01:00Z",
		"charge": 4,
		"status": "Unavailable",
		"group": 1,
		"locationId": "2065-57688547"
	}, {
		"slotId": "IzIwNjUtNTc2ODg1NDcjMjA2NSMyMDIwLTA0LTIzVDE4OjAwOjAwWiMyMDIwLTA0LTIzVDE5OjAwOjAwWiMzIzIwMjAtMDQtMjJUMjM6MDE6MDBaIw==",
		"start": "2020-04-23T18:00:00.000Z",
		"end": "2020-04-23T19:00:00.000Z",
		"expiry": "2020-04-22T23:01:00Z",
		"charge": 3,
		"status": "Unavailable",
		"group": 1,
		"locationId": "2065-57688547"
	}, {
		"slotId": "IzIwNjUtNTc2ODg1NDcjMjA2NSMyMDIwLTA0LTIzVDE5OjAwOjAwWiMyMDIwLTA0LTIzVDIwOjAwOjAwWiMzIzIwMjAtMDQtMjJUMjM6MDE6MDBaIw==",
		"start": "2020-04-23T19:00:00.000Z",
		"end": "2020-04-23T20:00:00.000Z",
		"expiry": "2020-04-22T23:01:00Z",
		"charge": 3,
		"status": "Unavailable",
		"group": 1,
		"locationId": "2065-57688547"
	}, {
		"slotId": "IzIwNjUtNTc2ODg1NDcjMjA2NSMyMDIwLTA0LTIzVDIwOjAwOjAwWiMyMDIwLTA0LTIzVDIxOjAwOjAwWiMyIzIwMjAtMDQtMjJUMjM6MDE6MDBaIw==",
		"start": "2020-04-23T20:00:00.000Z",
		"end": "2020-04-23T21:00:00.000Z",
		"expiry": "2020-04-22T23:01:00Z",
		"charge": 2,
		"status": "Unavailable",
		"group": 1,
		"locationId": "2065-57688547"
	}, {
		"slotId": "IzIwNjUtNTc2ODg1NDcjMjA2NSMyMDIwLTA0LTIzVDIxOjAwOjAwWiMyMDIwLTA0LTIzVDIyOjAwOjAwWiMyIzIwMjAtMDQtMjJUMjM6MDE6MDBaIw==",
		"start": "2020-04-23T21:00:00.000Z",
		"end": "2020-04-23T22:00:00.000Z",
		"expiry": "2020-04-22T23:01:00Z",
		"charge": 2,
		"status": "Unavailable",
		"group": 1,
		"locationId": "2065-57688547"
	}, {
		"slotId": "IzIwNjUtNTc2ODg1NDcjMjA2NSMyMDIwLTA0LTI0VDA3OjAwOjAwWiMyMDIwLTA0LTI0VDA4OjAwOjAwWiM3IzIwMjAtMDQtMjNUMjM6MDE6MDBaIw==",
		"start": "2020-04-24T07:00:00.000Z",
		"end": "2020-04-24T08:00:00.000Z",
		"expiry": "2020-04-23T23:01:00Z",
		"charge": 7,
		"status": "Unavailable",
		"group": 1,
		"locationId": "2065-57688547"
	}, {
		"slotId": "IzIwNjUtNTc2ODg1NDcjMjA2NSMyMDIwLTA0LTI0VDA4OjAwOjAwWiMyMDIwLTA0LTI0VDA5OjAwOjAwWiM3IzIwMjAtMDQtMjNUMjM6MDE6MDBaIw==",
		"start": "2020-04-24T08:00:00.000Z",
		"end": "2020-04-24T09:00:00.000Z",
		"expiry": "2020-04-23T23:01:00Z",
		"charge": 7,
		"status": "Unavailable",
		"group": 1,
		"locationId": "2065-57688547"
	}, {
		"slotId": "IzIwNjUtNTc2ODg1NDcjMjA2NSMyMDIwLTA0LTI0VDA5OjAwOjAwWiMyMDIwLTA0LTI0VDEwOjAwOjAwWiM2LjUjMjAyMC0wNC0yM1QyMzowMTowMFoj",
		"start": "2020-04-24T09:00:00.000Z",
		"end": "2020-04-24T10:00:00.000Z",
		"expiry": "2020-04-23T23:01:00Z",
		"charge": 6.5,
		"status": "Unavailable",
		"group": 1,
		"locationId": "2065-57688547"
	}, {
		"slotId": "IzIwNjUtNTc2ODg1NDcjMjA2NSMyMDIwLTA0LTI0VDEwOjAwOjAwWiMyMDIwLTA0LTI0VDExOjAwOjAwWiM2IzIwMjAtMDQtMjNUMjM6MDE6MDBaIw==",
		"start": "2020-04-24T10:00:00.000Z",
		"end": "2020-04-24T11:00:00.000Z",
		"expiry": "2020-04-23T23:01:00Z",
		"charge": 6,
		"status": "Unavailable",
		"group": 1,
		"locationId": "2065-57688547"
	}, {
		"slotId": "IzIwNjUtNTc2ODg1NDcjMjA2NSMyMDIwLTA0LTI0VDExOjAwOjAwWiMyMDIwLTA0LTI0VDEyOjAwOjAwWiM1LjUjMjAyMC0wNC0yM1QyMzowMTowMFoj",
		"start": "2020-04-24T11:00:00.000Z",
		"end": "2020-04-24T12:00:00.000Z",
		"expiry": "2020-04-23T23:01:00Z",
		"charge": 5.5,
		"status": "Unavailable",
		"group": 1,
		"locationId": "2065-57688547"
	}, {
		"slotId": "IzIwNjUtNTc2ODg1NDcjMjA2NSMyMDIwLTA0LTI0VDEyOjAwOjAwWiMyMDIwLTA0LTI0VDEzOjAwOjAwWiM2IzIwMjAtMDQtMjNUMjM6MDE6MDBaIw==",
		"start": "2020-04-24T12:00:00.000Z",
		"end": "2020-04-24T13:00:00.000Z",
		"expiry": "2020-04-23T23:01:00Z",
		"charge": 6,
		"status": "Unavailable",
		"group": 1,
		"locationId": "2065-57688547"
	}, {
		"slotId": "IzIwNjUtNTc2ODg1NDcjMjA2NSMyMDIwLTA0LTI0VDEzOjAwOjAwWiMyMDIwLTA0LTI0VDE0OjAwOjAwWiM1LjUjMjAyMC0wNC0yM1QyMzowMTowMFoj",
		"start": "2020-04-24T13:00:00.000Z",
		"end": "2020-04-24T14:00:00.000Z",
		"expiry": "2020-04-23T23:01:00Z",
		"charge": 5.5,
		"status": "Unavailable",
		"group": 1,
		"locationId": "2065-57688547"
	}, {
		"slotId": "IzIwNjUtNTc2ODg1NDcjMjA2NSMyMDIwLTA0LTI0VDE0OjAwOjAwWiMyMDIwLTA0LTI0VDE1OjAwOjAwWiM1IzIwMjAtMDQtMjNUMjM6MDE6MDBaIw==",
		"start": "2020-04-24T14:00:00.000Z",
		"end": "2020-04-24T15:00:00.000Z",
		"expiry": "2020-04-23T23:01:00Z",
		"charge": 5,
		"status": "Unavailable",
		"group": 1,
		"locationId": "2065-57688547"
	}, {
		"slotId": "IzIwNjUtNTc2ODg1NDcjMjA2NSMyMDIwLTA0LTI0VDE1OjAwOjAwWiMyMDIwLTA0LTI0VDE2OjAwOjAwWiM1IzIwMjAtMDQtMjNUMjM6MDE6MDBaIw==",
		"start": "2020-04-24T15:00:00.000Z",
		"end": "2020-04-24T16:00:00.000Z",
		"expiry": "2020-04-23T23:01:00Z",
		"charge": 5,
		"status": "Unavailable",
		"group": 1,
		"locationId": "2065-57688547"
	}, {
		"slotId": "IzIwNjUtNTc2ODg1NDcjMjA2NSMyMDIwLTA0LTI0VDE2OjAwOjAwWiMyMDIwLTA0LTI0VDE3OjAwOjAwWiM1LjUjMjAyMC0wNC0yM1QyMzowMTowMFoj",
		"start": "2020-04-24T16:00:00.000Z",
		"end": "2020-04-24T17:00:00.000Z",
		"expiry": "2020-04-23T23:01:00Z",
		"charge": 5.5,
		"status": "Unavailable",
		"group": 1,
		"locationId": "2065-57688547"
	}, {
		"slotId": "IzIwNjUtNTc2ODg1NDcjMjA2NSMyMDIwLTA0LTI0VDE3OjAwOjAwWiMyMDIwLTA0LTI0VDE4OjAwOjAwWiM1IzIwMjAtMDQtMjNUMjM6MDE6MDBaIw==",
		"start": "2020-04-24T17:00:00.000Z",
		"end": "2020-04-24T18:00:00.000Z",
		"expiry": "2020-04-23T23:01:00Z",
		"charge": 5,
		"status": "Unavailable",
		"group": 1,
		"locationId": "2065-57688547"
	}, {
		"slotId": "IzIwNjUtNTc2ODg1NDcjMjA2NSMyMDIwLTA0LTI0VDE4OjAwOjAwWiMyMDIwLTA0LTI0VDE5OjAwOjAwWiM1IzIwMjAtMDQtMjNUMjM6MDE6MDBaIw==",
		"start": "2020-04-24T18:00:00.000Z",
		"end": "2020-04-24T19:00:00.000Z",
		"expiry": "2020-04-23T23:01:00Z",
		"charge": 5,
		"status": "Unavailable",
		"group": 1,
		"locationId": "2065-57688547"
	}, {
		"slotId": "IzIwNjUtNTc2ODg1NDcjMjA2NSMyMDIwLTA0LTI0VDE5OjAwOjAwWiMyMDIwLTA0LTI0VDIwOjAwOjAwWiM0LjUjMjAyMC0wNC0yM1QyMzowMTowMFoj",
		"start": "2020-04-24T19:00:00.000Z",
		"end": "2020-04-24T20:00:00.000Z",
		"expiry": "2020-04-23T23:01:00Z",
		"charge": 4.5,
		"status": "Unavailable",
		"group": 1,
		"locationId": "2065-57688547"
	}, {
		"slotId": "IzIwNjUtNTc2ODg1NDcjMjA2NSMyMDIwLTA0LTI0VDIwOjAwOjAwWiMyMDIwLTA0LTI0VDIxOjAwOjAwWiMzLjUjMjAyMC0wNC0yM1QyMzowMTowMFoj",
		"start": "2020-04-24T20:00:00.000Z",
		"end": "2020-04-24T21:00:00.000Z",
		"expiry": "2020-04-23T23:01:00Z",
		"charge": 3.5,
		"status": "Unavailable",
		"group": 1,
		"locationId": "2065-57688547"
	}, {
		"slotId": "IzIwNjUtNTc2ODg1NDcjMjA2NSMyMDIwLTA0LTI0VDIxOjAwOjAwWiMyMDIwLTA0LTI0VDIyOjAwOjAwWiMzIzIwMjAtMDQtMjNUMjM6MDE6MDBaIw==",
		"start": "2020-04-24T21:00:00.000Z",
		"end": "2020-04-24T22:00:00.000Z",
		"expiry": "2020-04-23T23:01:00Z",
		"charge": 3,
		"status": "Unavailable",
		"group": 1,
		"locationId": "2065-57688547"
	}, {
		"slotId": "IzIwNjUtNTc2ODg1NDcjMjA2NSMyMDIwLTA0LTI1VDA3OjAwOjAwWiMyMDIwLTA0LTI1VDA4OjAwOjAwWiM3IzIwMjAtMDQtMjRUMjM6MDE6MDBaIw==",
		"start": "2020-04-25T07:00:00.000Z",
		"end": "2020-04-25T08:00:00.000Z",
		"expiry": "2020-04-24T23:01:00Z",
		"charge": 7,
		"status": "Unavailable",
		"group": 1,
		"locationId": "2065-57688547"
	}, {
		"slotId": "IzIwNjUtNTc2ODg1NDcjMjA2NSMyMDIwLTA0LTI1VDA4OjAwOjAwWiMyMDIwLTA0LTI1VDA5OjAwOjAwWiM3IzIwMjAtMDQtMjRUMjM6MDE6MDBaIw==",
		"start": "2020-04-25T08:00:00.000Z",
		"end": "2020-04-25T09:00:00.000Z",
		"expiry": "2020-04-24T23:01:00Z",
		"charge": 7,
		"status": "Unavailable",
		"group": 1,
		"locationId": "2065-57688547"
	}, {
		"slotId": "IzIwNjUtNTc2ODg1NDcjMjA2NSMyMDIwLTA0LTI1VDA5OjAwOjAwWiMyMDIwLTA0LTI1VDEwOjAwOjAwWiM3IzIwMjAtMDQtMjRUMjM6MDE6MDBaIw==",
		"start": "2020-04-25T09:00:00.000Z",
		"end": "2020-04-25T10:00:00.000Z",
		"expiry": "2020-04-24T23:01:00Z",
		"charge": 7,
		"status": "Unavailable",
		"group": 1,
		"locationId": "2065-57688547"
	}, {
		"slotId": "IzIwNjUtNTc2ODg1NDcjMjA2NSMyMDIwLTA0LTI1VDEwOjAwOjAwWiMyMDIwLTA0LTI1VDExOjAwOjAwWiM3IzIwMjAtMDQtMjRUMjM6MDE6MDBaIw==",
		"start": "2020-04-25T10:00:00.000Z",
		"end": "2020-04-25T11:00:00.000Z",
		"expiry": "2020-04-24T23:01:00Z",
		"charge": 7,
		"status": "Unavailable",
		"group": 1,
		"locationId": "2065-57688547"
	}, {
		"slotId": "IzIwNjUtNTc2ODg1NDcjMjA2NSMyMDIwLTA0LTI1VDExOjAwOjAwWiMyMDIwLTA0LTI1VDEyOjAwOjAwWiM2IzIwMjAtMDQtMjRUMjM6MDE6MDBaIw==",
		"start": "2020-04-25T11:00:00.000Z",
		"end": "2020-04-25T12:00:00.000Z",
		"expiry": "2020-04-24T23:01:00Z",
		"charge": 6,
		"status": "Unavailable",
		"group": 1,
		"locationId": "2065-57688547"
	}, {
		"slotId": "IzIwNjUtNTc2ODg1NDcjMjA2NSMyMDIwLTA0LTI1VDEyOjAwOjAwWiMyMDIwLTA0LTI1VDEzOjAwOjAwWiM2LjUjMjAyMC0wNC0yNFQyMzowMTowMFoj",
		"start": "2020-04-25T12:00:00.000Z",
		"end": "2020-04-25T13:00:00.000Z",
		"expiry": "2020-04-24T23:01:00Z",
		"charge": 6.5,
		"status": "Unavailable",
		"group": 1,
		"locationId": "2065-57688547"
	}, {
		"slotId": "IzIwNjUtNTc2ODg1NDcjMjA2NSMyMDIwLTA0LTI1VDEzOjAwOjAwWiMyMDIwLTA0LTI1VDE0OjAwOjAwWiM1LjUjMjAyMC0wNC0yNFQyMzowMTowMFoj",
		"start": "2020-04-25T13:00:00.000Z",
		"end": "2020-04-25T14:00:00.000Z",
		"expiry": "2020-04-24T23:01:00Z",
		"charge": 5.5,
		"status": "Unavailable",
		"group": 1,
		"locationId": "2065-57688547"
	}, {
		"slotId": "IzIwNjUtNTc2ODg1NDcjMjA2NSMyMDIwLTA0LTI1VDE0OjAwOjAwWiMyMDIwLTA0LTI1VDE1OjAwOjAwWiM1IzIwMjAtMDQtMjRUMjM6MDE6MDBaIw==",
		"start": "2020-04-25T14:00:00.000Z",
		"end": "2020-04-25T15:00:00.000Z",
		"expiry": "2020-04-24T23:01:00Z",
		"charge": 5,
		"status": "Unavailable",
		"group": 1,
		"locationId": "2065-57688547"
	}, {
		"slotId": "IzIwNjUtNTc2ODg1NDcjMjA2NSMyMDIwLTA0LTI1VDE1OjAwOjAwWiMyMDIwLTA0LTI1VDE2OjAwOjAwWiM0LjUjMjAyMC0wNC0yNFQyMzowMTowMFoj",
		"start": "2020-04-25T15:00:00.000Z",
		"end": "2020-04-25T16:00:00.000Z",
		"expiry": "2020-04-24T23:01:00Z",
		"charge": 4.5,
		"status": "Unavailable",
		"group": 1,
		"locationId": "2065-57688547"
	}, {
		"slotId": "IzIwNjUtNTc2ODg1NDcjMjA2NSMyMDIwLTA0LTI1VDE2OjAwOjAwWiMyMDIwLTA0LTI1VDE3OjAwOjAwWiM0LjUjMjAyMC0wNC0yNFQyMzowMTowMFoj",
		"start": "2020-04-25T16:00:00.000Z",
		"end": "2020-04-25T17:00:00.000Z",
		"expiry": "2020-04-24T23:01:00Z",
		"charge": 4.5,
		"status": "Unavailable",
		"group": 1,
		"locationId": "2065-57688547"
	}, {
		"slotId": "IzIwNjUtNTc2ODg1NDcjMjA2NSMyMDIwLTA0LTI1VDE3OjAwOjAwWiMyMDIwLTA0LTI1VDE4OjAwOjAwWiM0LjUjMjAyMC0wNC0yNFQyMzowMTowMFoj",
		"start": "2020-04-25T17:00:00.000Z",
		"end": "2020-04-25T18:00:00.000Z",
		"expiry": "2020-04-24T23:01:00Z",
		"charge": 4.5,
		"status": "Unavailable",
		"group": 1,
		"locationId": "2065-57688547"
	}, {
		"slotId": "IzIwNjUtNTc2ODg1NDcjMjA2NSMyMDIwLTA0LTI1VDE4OjAwOjAwWiMyMDIwLTA0LTI1VDE5OjAwOjAwWiM1IzIwMjAtMDQtMjRUMjM6MDE6MDBaIw==",
		"start": "2020-04-25T18:00:00.000Z",
		"end": "2020-04-25T19:00:00.000Z",
		"expiry": "2020-04-24T23:01:00Z",
		"charge": 5,
		"status": "Unavailable",
		"group": 1,
		"locationId": "2065-57688547"
	}, {
		"slotId": "IzIwNjUtNTc2ODg1NDcjMjA2NSMyMDIwLTA0LTI1VDE5OjAwOjAwWiMyMDIwLTA0LTI1VDIwOjAwOjAwWiM0IzIwMjAtMDQtMjRUMjM6MDE6MDBaIw==",
		"start": "2020-04-25T19:00:00.000Z",
		"end": "2020-04-25T20:00:00.000Z",
		"expiry": "2020-04-24T23:01:00Z",
		"charge": 4,
		"status": "Unavailable",
		"group": 1,
		"locationId": "2065-57688547"
	}, {
		"slotId": "IzIwNjUtNTc2ODg1NDcjMjA2NSMyMDIwLTA0LTI1VDIwOjAwOjAwWiMyMDIwLTA0LTI1VDIxOjAwOjAwWiM0IzIwMjAtMDQtMjRUMjM6MDE6MDBaIw==",
		"start": "2020-04-25T20:00:00.000Z",
		"end": "2020-04-25T21:00:00.000Z",
		"expiry": "2020-04-24T23:01:00Z",
		"charge": 4,
		"status": "Unavailable",
		"group": 1,
		"locationId": "2065-57688547"
	}, {
		"slotId": "2020-04-25T22:00:00+01:00#2020-04-25T23:00:00+01:00",
		"start": "2020-04-25T21:00:00.000Z",
		"end": "2020-04-25T22:00:00.000Z",
		"status": "UnAvailable"
	}, {
		"slotId": "2020-04-26T08:00:00+01:00#2020-04-26T09:00:00+01:00",
		"start": "2020-04-26T07:00:00.000Z",
		"end": "2020-04-26T08:00:00.000Z",
		"status": "UnAvailable"
	}, {
		"slotId": "2020-04-26T09:00:00+01:00#2020-04-26T10:00:00+01:00",
		"start": "2020-04-26T08:00:00.000Z",
		"end": "2020-04-26T09:00:00.000Z",
		"status": "UnAvailable"
	}, {
		"slotId": "IzIwNjUtNTc2ODg1NDcjMjA2NSMyMDIwLTA0LTI2VDA5OjAwOjAwWiMyMDIwLTA0LTI2VDEwOjAwOjAwWiM3IzIwMjAtMDQtMjVUMjM6MDE6MDBaIw==",
		"start": "2020-04-26T09:00:00.000Z",
		"end": "2020-04-26T10:00:00.000Z",
		"expiry": "2020-04-25T23:01:00Z",
		"charge": 7,
		"status": "Unavailable",
		"group": 1,
		"locationId": "2065-57688547"
	}, {
		"slotId": "IzIwNjUtNTc2ODg1NDcjMjA2NSMyMDIwLTA0LTI2VDEwOjAwOjAwWiMyMDIwLTA0LTI2VDExOjAwOjAwWiM3IzIwMjAtMDQtMjVUMjM6MDE6MDBaIw==",
		"start": "2020-04-26T10:00:00.000Z",
		"end": "2020-04-26T11:00:00.000Z",
		"expiry": "2020-04-25T23:01:00Z",
		"charge": 7,
		"status": "Unavailable",
		"group": 1,
		"locationId": "2065-57688547"
	}, {
		"slotId": "IzIwNjUtNTc2ODg1NDcjMjA2NSMyMDIwLTA0LTI2VDExOjAwOjAwWiMyMDIwLTA0LTI2VDEyOjAwOjAwWiM2IzIwMjAtMDQtMjVUMjM6MDE6MDBaIw==",
		"start": "2020-04-26T11:00:00.000Z",
		"end": "2020-04-26T12:00:00.000Z",
		"expiry": "2020-04-25T23:01:00Z",
		"charge": 6,
		"status": "Unavailable",
		"group": 1,
		"locationId": "2065-57688547"
	}, {
		"slotId": "IzIwNjUtNTc2ODg1NDcjMjA2NSMyMDIwLTA0LTI2VDEyOjAwOjAwWiMyMDIwLTA0LTI2VDEzOjAwOjAwWiM1IzIwMjAtMDQtMjVUMjM6MDE6MDBaIw==",
		"start": "2020-04-26T12:00:00.000Z",
		"end": "2020-04-26T13:00:00.000Z",
		"expiry": "2020-04-25T23:01:00Z",
		"charge": 5,
		"status": "Unavailable",
		"group": 1,
		"locationId": "2065-57688547"
	}, {
		"slotId": "IzIwNjUtNTc2ODg1NDcjMjA2NSMyMDIwLTA0LTI2VDEzOjAwOjAwWiMyMDIwLTA0LTI2VDE0OjAwOjAwWiM1LjUjMjAyMC0wNC0yNVQyMzowMTowMFoj",
		"start": "2020-04-26T13:00:00.000Z",
		"end": "2020-04-26T14:00:00.000Z",
		"expiry": "2020-04-25T23:01:00Z",
		"charge": 5.5,
		"status": "Unavailable",
		"group": 1,
		"locationId": "2065-57688547"
	}, {
		"slotId": "2020-04-26T15:00:00+01:00#2020-04-26T16:00:00+01:00",
		"start": "2020-04-26T14:00:00.000Z",
		"end": "2020-04-26T15:00:00.000Z",
		"status": "UnAvailable"
	}, {
		"slotId": "2020-04-26T16:00:00+01:00#2020-04-26T17:00:00+01:00",
		"start": "2020-04-26T15:00:00.000Z",
		"end": "2020-04-26T16:00:00.000Z",
		"status": "UnAvailable"
	}, {
		"slotId": "2020-04-26T17:00:00+01:00#2020-04-26T18:00:00+01:00",
		"start": "2020-04-26T16:00:00.000Z",
		"end": "2020-04-26T17:00:00.000Z",
		"status": "UnAvailable"
	}, {
		"slotId": "IzIwNjUtNTc2ODg1NDcjMjA2NSMyMDIwLTA0LTI2VDE3OjAwOjAwWiMyMDIwLTA0LTI2VDE4OjAwOjAwWiM2IzIwMjAtMDQtMjVUMjM6MDE6MDBaIw==",
		"start": "2020-04-26T17:00:00.000Z",
		"end": "2020-04-26T18:00:00.000Z",
		"expiry": "2020-04-25T23:01:00Z",
		"charge": 6,
		"status": "Unavailable",
		"group": 1,
		"locationId": "2065-57688547"
	}, {
		"slotId": "IzIwNjUtNTc2ODg1NDcjMjA2NSMyMDIwLTA0LTI2VDE4OjAwOjAwWiMyMDIwLTA0LTI2VDE5OjAwOjAwWiM1LjUjMjAyMC0wNC0yNVQyMzowMTowMFoj",
		"start": "2020-04-26T18:00:00.000Z",
		"end": "2020-04-26T19:00:00.000Z",
		"expiry": "2020-04-25T23:01:00Z",
		"charge": 5.5,
		"status": "Unavailable",
		"group": 1,
		"locationId": "2065-57688547"
	}, {
		"slotId": "IzIwNjUtNTc2ODg1NDcjMjA2NSMyMDIwLTA0LTI2VDE5OjAwOjAwWiMyMDIwLTA0LTI2VDIwOjAwOjAwWiM0LjUjMjAyMC0wNC0yNVQyMzowMTowMFoj",
		"start": "2020-04-26T19:00:00.000Z",
		"end": "2020-04-26T20:00:00.000Z",
		"expiry": "2020-04-25T23:01:00Z",
		"charge": 4.5,
		"status": "Unavailable",
		"group": 1,
		"locationId": "2065-57688547"
	}, {
		"slotId": "IzIwNjUtNTc2ODg1NDcjMjA2NSMyMDIwLTA0LTI2VDIwOjAwOjAwWiMyMDIwLTA0LTI2VDIxOjAwOjAwWiM0IzIwMjAtMDQtMjVUMjM6MDE6MDBaIw==",
		"start": "2020-04-26T20:00:00.000Z",
		"end": "2020-04-26T21:00:00.000Z",
		"expiry": "2020-04-25T23:01:00Z",
		"charge": 4,
		"status": "Unavailable",
		"group": 1,
		"locationId": "2065-57688547"
	}, {
		"slotId": "2020-04-26T22:00:00+01:00#2020-04-26T23:00:00+01:00",
		"start": "2020-04-26T21:00:00.000Z",
		"end": "2020-04-26T22:00:00.000Z",
		"status": "UnAvailable"
	}, {
		"slotId": "IzIwNjUtNTc2ODg1NDcjMjA2NSMyMDIwLTA0LTI3VDA3OjAwOjAwWiMyMDIwLTA0LTI3VDA4OjAwOjAwWiM2IzIwMjAtMDQtMjZUMjM6MDE6MDBaIw==",
		"start": "2020-04-27T07:00:00.000Z",
		"end": "2020-04-27T08:00:00.000Z",
		"expiry": "2020-04-26T23:01:00Z",
		"charge": 6,
		"status": "Unavailable",
		"group": 1,
		"locationId": "2065-57688547"
	}, {
		"slotId": "IzIwNjUtNTc2ODg1NDcjMjA2NSMyMDIwLTA0LTI3VDA4OjAwOjAwWiMyMDIwLTA0LTI3VDA5OjAwOjAwWiM2IzIwMjAtMDQtMjZUMjM6MDE6MDBaIw==",
		"start": "2020-04-27T08:00:00.000Z",
		"end": "2020-04-27T09:00:00.000Z",
		"expiry": "2020-04-26T23:01:00Z",
		"charge": 6,
		"status": "Unavailable",
		"group": 1,
		"locationId": "2065-57688547"
	}, {
		"slotId": "IzIwNjUtNTc2ODg1NDcjMjA2NSMyMDIwLTA0LTI3VDA5OjAwOjAwWiMyMDIwLTA0LTI3VDEwOjAwOjAwWiM1LjUjMjAyMC0wNC0yNlQyMzowMTowMFoj",
		"start": "2020-04-27T09:00:00.000Z",
		"end": "2020-04-27T10:00:00.000Z",
		"expiry": "2020-04-26T23:01:00Z",
		"charge": 5.5,
		"status": "Unavailable",
		"group": 1,
		"locationId": "2065-57688547"
	}, {
		"slotId": "IzIwNjUtNTc2ODg1NDcjMjA2NSMyMDIwLTA0LTI3VDEwOjAwOjAwWiMyMDIwLTA0LTI3VDExOjAwOjAwWiM0LjUjMjAyMC0wNC0yNlQyMzowMTowMFoj",
		"start": "2020-04-27T10:00:00.000Z",
		"end": "2020-04-27T11:00:00.000Z",
		"expiry": "2020-04-26T23:01:00Z",
		"charge": 4.5,
		"status": "Unavailable",
		"group": 1,
		"locationId": "2065-57688547"
	}, {
		"slotId": "IzIwNjUtNTc2ODg1NDcjMjA2NSMyMDIwLTA0LTI3VDExOjAwOjAwWiMyMDIwLTA0LTI3VDEyOjAwOjAwWiM0IzIwMjAtMDQtMjZUMjM6MDE6MDBaIw==",
		"start": "2020-04-27T11:00:00.000Z",
		"end": "2020-04-27T12:00:00.000Z",
		"expiry": "2020-04-26T23:01:00Z",
		"charge": 4,
		"status": "Unavailable",
		"group": 1,
		"locationId": "2065-57688547"
	}, {
		"slotId": "IzIwNjUtNTc2ODg1NDcjMjA2NSMyMDIwLTA0LTI3VDEyOjAwOjAwWiMyMDIwLTA0LTI3VDEzOjAwOjAwWiM0IzIwMjAtMDQtMjZUMjM6MDE6MDBaIw==",
		"start": "2020-04-27T12:00:00.000Z",
		"end": "2020-04-27T13:00:00.000Z",
		"expiry": "2020-04-26T23:01:00Z",
		"charge": 4,
		"status": "Unavailable",
		"group": 1,
		"locationId": "2065-57688547"
	}, {
		"slotId": "IzIwNjUtNTc2ODg1NDcjMjA2NSMyMDIwLTA0LTI3VDEzOjAwOjAwWiMyMDIwLTA0LTI3VDE0OjAwOjAwWiMzLjUjMjAyMC0wNC0yNlQyMzowMTowMFoj",
		"start": "2020-04-27T13:00:00.000Z",
		"end": "2020-04-27T14:00:00.000Z",
		"expiry": "2020-04-26T23:01:00Z",
		"charge": 3.5,
		"status": "Unavailable",
		"group": 1,
		"locationId": "2065-57688547"
	}, {
		"slotId": "IzIwNjUtNTc2ODg1NDcjMjA2NSMyMDIwLTA0LTI3VDE0OjAwOjAwWiMyMDIwLTA0LTI3VDE1OjAwOjAwWiMzLjUjMjAyMC0wNC0yNlQyMzowMTowMFoj",
		"start": "2020-04-27T14:00:00.000Z",
		"end": "2020-04-27T15:00:00.000Z",
		"expiry": "2020-04-26T23:01:00Z",
		"charge": 3.5,
		"status": "Unavailable",
		"group": 1,
		"locationId": "2065-57688547"
	}, {
		"slotId": "IzIwNjUtNTc2ODg1NDcjMjA2NSMyMDIwLTA0LTI3VDE1OjAwOjAwWiMyMDIwLTA0LTI3VDE2OjAwOjAwWiMzLjUjMjAyMC0wNC0yNlQyMzowMTowMFoj",
		"start": "2020-04-27T15:00:00.000Z",
		"end": "2020-04-27T16:00:00.000Z",
		"expiry": "2020-04-26T23:01:00Z",
		"charge": 3.5,
		"status": "Unavailable",
		"group": 1,
		"locationId": "2065-57688547"
	}, {
		"slotId": "IzIwNjUtNTc2ODg1NDcjMjA2NSMyMDIwLTA0LTI3VDE2OjAwOjAwWiMyMDIwLTA0LTI3VDE3OjAwOjAwWiM0IzIwMjAtMDQtMjZUMjM6MDE6MDBaIw==",
		"start": "2020-04-27T16:00:00.000Z",
		"end": "2020-04-27T17:00:00.000Z",
		"expiry": "2020-04-26T23:01:00Z",
		"charge": 4,
		"status": "Unavailable",
		"group": 1,
		"locationId": "2065-57688547"
	}, {
		"slotId": "IzIwNjUtNTc2ODg1NDcjMjA2NSMyMDIwLTA0LTI3VDE3OjAwOjAwWiMyMDIwLTA0LTI3VDE4OjAwOjAwWiM0IzIwMjAtMDQtMjZUMjM6MDE6MDBaIw==",
		"start": "2020-04-27T17:00:00.000Z",
		"end": "2020-04-27T18:00:00.000Z",
		"expiry": "2020-04-26T23:01:00Z",
		"charge": 4,
		"status": "Unavailable",
		"group": 1,
		"locationId": "2065-57688547"
	}, {
		"slotId": "IzIwNjUtNTc2ODg1NDcjMjA2NSMyMDIwLTA0LTI3VDE4OjAwOjAwWiMyMDIwLTA0LTI3VDE5OjAwOjAwWiM0IzIwMjAtMDQtMjZUMjM6MDE6MDBaIw==",
		"start": "2020-04-27T18:00:00.000Z",
		"end": "2020-04-27T19:00:00.000Z",
		"expiry": "2020-04-26T23:01:00Z",
		"charge": 4,
		"status": "Unavailable",
		"group": 1,
		"locationId": "2065-57688547"
	}, {
		"slotId": "IzIwNjUtNTc2ODg1NDcjMjA2NSMyMDIwLTA0LTI3VDE5OjAwOjAwWiMyMDIwLTA0LTI3VDIwOjAwOjAwWiMzLjUjMjAyMC0wNC0yNlQyMzowMTowMFoj",
		"start": "2020-04-27T19:00:00.000Z",
		"end": "2020-04-27T20:00:00.000Z",
		"expiry": "2020-04-26T23:01:00Z",
		"charge": 3.5,
		"status": "Unavailable",
		"group": 1,
		"locationId": "2065-57688547"
	}, {
		"slotId": "IzIwNjUtNTc2ODg1NDcjMjA2NSMyMDIwLTA0LTI3VDIwOjAwOjAwWiMyMDIwLTA0LTI3VDIxOjAwOjAwWiMyLjUjMjAyMC0wNC0yNlQyMzowMTowMFoj",
		"start": "2020-04-27T20:00:00.000Z",
		"end": "2020-04-27T21:00:00.000Z",
		"expiry": "2020-04-26T23:01:00Z",
		"charge": 2.5,
		"status": "Unavailable",
		"group": 1,
		"locationId": "2065-57688547"
	}, {
		"slotId": "IzIwNjUtNTc2ODg1NDcjMjA2NSMyMDIwLTA0LTI3VDIxOjAwOjAwWiMyMDIwLTA0LTI3VDIyOjAwOjAwWiMyIzIwMjAtMDQtMjZUMjM6MDE6MDBaIw==",
		"start": "2020-04-27T21:00:00.000Z",
		"end": "2020-04-27T22:00:00.000Z",
		"expiry": "2020-04-26T23:01:00Z",
		"charge": 2,
		"status": "Unavailable",
		"group": 1,
		"locationId": "2065-57688547"
	}],
	"availableSlotGroups": [1, 4],
	"currentSlotGroup": 1,
	"selectedDate": "2020-04-21"
}